{"DOCTYPE":"MULTI_DIR_ANIMATION","namedSheets":{"move":{"src":"media\/entity\/enemy\/jungle-fish-gear.png","xCount":13,"offX":0,"offY":0,"width":48,"height":56}},"shapeType":"Y_FLAT","wallY":0.3,"SUB":[{"sheet":"move","dirs":"6","flipX":[0,0,0,1,1,1],"tileOffsets":[0,13,26,26,13,0],"SUB":[{"name":"idle","time":0.1,"repeat":true,"frames":[0,1,2,3]},{"name":"move","time":0.1,"repeat":true,"frames":[4,5,6,7]},{"name":"charge","time":0.07,"repeat":true,"frames":[8,8],"framesGfxOffset":[0,0,1,0]},{"name":"preJump","time":0.07,"repeat":true,"frames":[8]},{"name":"jump","time":0.07,"repeat":true,"frames":[9]},{"name":"dashMove","time":0.07,"repeat":true,"frames":[10]},{"name":"dash","time":0.07,"repeat":true,"frames":[11]},{"name":"damage","time":0.05,"repeat":true,"frames":[12,12],"framesGfxOffset":[0,0,1,0]}]}]}