{"name":"final-dng\/g\/room-s-2","levels":[{"height":-96},{"height":0},{"height":32}],"mapWidth":50,"mapHeight":45,"masterLevel":1,"entities":[{"type":"Door","x":384,"y":640,"level":1,"settings":{"name":"entrance","doorType":"DEFAULT","dir":"NORTH","transitionType":"REGULAR","mapId":4,"map":"final-dng.g.room-s-1","marker":"exit","variation":""}},{"type":"Door","x":592,"y":176,"level":1,"settings":{"name":"exit","doorType":"DEFAULT","dir":"SOUTH","transitionType":"REGULAR","mapId":5,"map":"final-dng.g.room-s-3","marker":"entrance","variation":"","condition":"map.finalDoor"}},{"type":"Note","x":580,"y":628,"level":1,"settings":{"name":"","size":{"x":184,"y":64},"zHeight":0,"text":"Introduce Ferro Element Basics\n- Move it around\n- Activate Switches\n- Activate Temporary switches","mapId":6}},{"type":"FerroSpot","x":384,"y":448,"level":1,"settings":{"name":"firstFerro","source":true,"mapId":7,"activeCondition":"map.ferroThere"}},{"type":"ScalableProp","x":448,"y":368,"level":1,"settings":{"name":"","size":{"x":208,"y":8},"patternOffset":{"x":0,"y":0},"timeOffset":0,"blockNavMap":false,"mapId":8,"propConfig":{"sheet":"final-dng-inner","name":"fenceH","ends":{"west":"","east":""}}}},{"type":"ScalableProp","x":176,"y":368,"level":1,"settings":{"name":"","size":{"x":80,"y":8},"patternOffset":{"x":0,"y":0},"timeOffset":0,"blockNavMap":false,"mapId":9,"propConfig":{"sheet":"final-dng-inner","name":"fenceH","ends":{"west":"","east":""}}}},{"type":"ScalableProp","x":176,"y":424,"level":1,"settings":{"name":"","size":{"x":144,"y":8},"patternOffset":{"x":0,"y":0},"timeOffset":0,"blockNavMap":false,"mapId":10,"propConfig":{"sheet":"final-dng-inner","name":"fenceH","ends":{"west":"","east":""}}}},{"type":"WallVertical","x":176,"y":376,"level":1,"settings":{"name":"","size":{"x":8,"y":48},"skipRender":false,"topEnd":"STOP","bottomEnd":"STOP","collType":"NPBLOCK","wallZHeight":24,"noNavMapBlock":false,"mapId":11}},{"type":"OneTimeSwitch","x":544,"y":464,"level":1,"settings":{"name":"","switchType":"ferroSwitch","activeTime":0,"fixCount":0,"fastMode":false,"mapId":12,"variable":"map.barrierA","addValue":""}},{"type":"WallVertical","x":320,"y":360,"level":1,"settings":{"name":"","size":{"x":8,"y":64},"skipRender":false,"topEnd":"STOP","bottomEnd":"STOP","collType":"BLOCK","wallZHeight":24,"noNavMapBlock":false,"mapId":13,"condition":"!map.barrierA"}},{"type":"ScalableProp","x":192,"y":496,"level":1,"settings":{"name":"","size":{"x":128,"y":8},"patternOffset":{"x":0,"y":0},"timeOffset":0,"blockNavMap":false,"mapId":14,"propConfig":{"sheet":"final-dng-inner","name":"fenceH","ends":{"west":"","east":""}}}},{"type":"ScalableProp","x":320,"y":424,"level":1,"settings":{"name":"","size":{"x":8,"y":80},"patternOffset":{"x":0,"y":0},"timeOffset":0,"blockNavMap":false,"mapId":17,"propConfig":{"sheet":"final-dng-inner","name":"fenceV","ends":{"north":"NORTH_WEST","south":"SOUTH_WEST"}}}},{"type":"ScalableProp","x":680,"y":408,"level":1,"settings":{"name":"","size":{"x":8,"y":168},"patternOffset":{"x":0,"y":0},"timeOffset":0,"blockNavMap":false,"mapId":18,"propConfig":{"sheet":"final-dng-inner","name":"fenceV","ends":{"north":"NORTH_MIX","south":"SOUTH_END"}}}},{"type":"Prop","x":656,"y":376,"level":1,"settings":{"name":"","mapId":19,"propType":{"sheet":"final-dng-inner","name":"slopeSWmid"},"propAnim":"","condAnims":[]}},{"type":"Prop","x":672,"y":392,"level":1,"settings":{"name":"","mapId":20,"propType":{"sheet":"final-dng-inner","name":"slopeSWbottom"},"propAnim":"","condAnims":[]}},{"type":"OneTimeSwitch","x":192,"y":392,"level":1,"settings":{"name":"","switchType":"ferroSwitch","activeTime":0.1,"fixCount":0,"fastMode":false,"mapId":21,"variable":"tmp.barrierB","addValue":""}},{"type":"OneTimeSwitch","x":280,"y":392,"level":1,"settings":{"name":"","switchType":"ferroSwitch","activeTime":0.1,"fixCount":0,"fastMode":false,"mapId":22,"variable":"tmp.barrierC","addValue":""}},{"type":"ScalableProp","x":168,"y":424,"level":1,"settings":{"name":"","size":{"x":8,"y":64},"patternOffset":{"x":0,"y":0},"timeOffset":0,"blockNavMap":false,"mapId":24,"propConfig":{"sheet":"final-dng-inner","name":"fenceV","ends":{"north":"NORTH_EAST","south":"SOUTH_EAST"}}}},{"type":"Prop","x":176,"y":488,"level":1,"settings":{"name":"","mapId":25,"propType":{"sheet":"final-dng-inner","name":"slopeSWmid"},"propAnim":"","condAnims":[]}},{"type":"WallHorizontal","x":112,"y":472,"level":1,"settings":{"name":"","size":{"x":56,"y":8},"skipRender":false,"leftEnd":"STOP","rightEnd":"STOP","collType":"BLOCK","wallZHeight":24,"noNavMapBlock":false,"mapId":26,"condition":"!tmp.barrierB && !tmp.barrierBEscape"}},{"type":"FerroLine","x":396,"y":496,"level":1,"settings":{"name":"","size":{"x":8,"y":32},"spot":{"global":true,"name":"firstFerro"},"mapId":27}},{"type":"FerroRespawner","x":392,"y":528,"level":1,"settings":{"name":"","mapId":28}},{"type":"FerroSpot","x":592,"y":240,"level":1,"settings":{"name":"","source":false,"variable":"map.finalDoor","mapId":29,"activeCondition":""}},{"type":"FerroLine","x":604,"y":200,"level":1,"settings":{"name":"","size":{"x":8,"y":40},"mapId":30}},{"type":"WallHorizontal","x":112,"y":304,"level":1,"settings":{"name":"","size":{"x":56,"y":8},"skipRender":false,"leftEnd":"STOP","rightEnd":"STOP","collType":"BLOCK","wallZHeight":24,"noNavMapBlock":false,"mapId":32,"condition":"!tmp.barrierC && !tmp.barrierCEscape"}},{"type":"ScalableProp","x":168,"y":296,"level":1,"settings":{"name":"","size":{"x":8,"y":80},"patternOffset":{"x":0,"y":0},"timeOffset":0,"blockNavMap":false,"mapId":33,"propConfig":{"sheet":"final-dng-inner","name":"fenceV","ends":{"north":"NORTH_EAST","south":"SOUTH_EAST"}}}},{"type":"Prop","x":176,"y":280,"level":1,"settings":{"name":"","mapId":34,"propType":{"sheet":"final-dng-inner","name":"slopeNWmid"},"propAnim":"","condAnims":[]}},{"type":"ScalableProp","x":192,"y":280,"level":1,"settings":{"name":"","size":{"x":64,"y":8},"patternOffset":{"x":0,"y":0},"timeOffset":0,"blockNavMap":false,"mapId":35,"propConfig":{"sheet":"final-dng-inner","name":"fenceH","ends":{"west":"","east":""}}}},{"type":"TouchTrigger","x":112,"y":464,"level":1,"settings":{"name":"","size":{"x":56,"y":8},"type":"WHILE_TOUCH_TRUE","zHeight":16,"reactToParty":false,"mapId":36,"variable":"tmp.barrierBEscape"}},{"type":"ScalableProp","x":368,"y":312,"level":1,"settings":{"name":"","size":{"x":8,"y":48},"patternOffset":{"x":0,"y":0},"timeOffset":0,"blockNavMap":false,"mapId":37,"propConfig":{"sheet":"final-dng-inner","name":"fenceV","ends":{"north":"NORTH_WEST","south":"SOUTH_WEST"}}}},{"type":"ScalableProp","x":424,"y":312,"level":1,"settings":{"name":"","size":{"x":8,"y":48},"patternOffset":{"x":0,"y":0},"timeOffset":0,"blockNavMap":false,"mapId":38,"propConfig":{"sheet":"final-dng-inner","name":"fenceV","ends":{"north":"NORTH_EAST","south":"SOUTH_EAST"}}}},{"type":"Prop","x":432,"y":296,"level":1,"settings":{"name":"","mapId":39,"propType":{"sheet":"final-dng-inner","name":"slopeNWmid"},"propAnim":"","condAnims":[]}},{"type":"Prop","x":448,"y":280,"level":1,"settings":{"name":"","mapId":40,"propType":{"sheet":"final-dng-inner","name":"slopeNWmid"},"propAnim":"","condAnims":[]}},{"type":"Prop","x":432,"y":360,"level":1,"settings":{"name":"","mapId":41,"propType":{"sheet":"final-dng-inner","name":"slopeSWmid"},"propAnim":"","condAnims":[]}},{"type":"Prop","x":352,"y":296,"level":1,"settings":{"name":"","mapId":43,"propType":{"sheet":"final-dng-inner","name":"slopeNEmid"},"propAnim":"","condAnims":[]}},{"type":"Prop","x":336,"y":280,"level":1,"settings":{"name":"","mapId":44,"propType":{"sheet":"final-dng-inner","name":"slopeNEmid"},"propAnim":"","condAnims":[]}},{"type":"ScalableProp","x":464,"y":280,"level":1,"settings":{"name":"","size":{"x":80,"y":8},"patternOffset":{"x":0,"y":0},"timeOffset":0,"blockNavMap":false,"mapId":45,"propConfig":{"sheet":"final-dng-inner","name":"fenceH","ends":{"west":"","east":""}}}},{"type":"OneTimeSwitch","x":280,"y":336,"level":1,"settings":{"name":"","switchType":"ferroSwitch","activeTime":0.1,"fixCount":0,"fastMode":false,"mapId":46,"variable":"tmp.barrierD","addValue":""}},{"type":"ScalableProp","x":320,"y":280,"level":1,"settings":{"name":"","size":{"x":16,"y":8},"patternOffset":{"x":0,"y":0},"timeOffset":0,"blockNavMap":false,"mapId":47,"propConfig":{"sheet":"final-dng-inner","name":"fenceH","ends":{"west":"","east":""}}}},{"type":"BallChanger","x":276,"y":276,"level":1,"settings":{"name":"","mapId":50,"condition":"!map.barrierE","changerType":{"type":"CHANGE_ELEMENT","settings":{"element":"SHOCK"}}}},{"type":"WallHorizontal","x":264,"y":312,"level":1,"settings":{"name":"","size":{"x":48,"y":8},"skipRender":false,"leftEnd":"STOP","rightEnd":"STOP","collType":"NPBLOCK","wallZHeight":24,"noNavMapBlock":false,"mapId":51,"condition":"!map.barrierE"}},{"type":"ScalableProp","x":320,"y":352,"level":1,"settings":{"name":"","size":{"x":48,"y":8},"patternOffset":{"x":0,"y":0},"timeOffset":0,"blockNavMap":false,"mapId":52,"propConfig":{"sheet":"final-dng-inner","name":"fenceH","ends":{"west":"","east":""}}}},{"type":"WallVertical","x":328,"y":224,"level":1,"settings":{"name":"","size":{"x":8,"y":56},"skipRender":false,"topEnd":"STOP","bottomEnd":"STOP","collType":"BLOCK","wallZHeight":24,"noNavMapBlock":false,"mapId":54,"condition":"!tmp.barrierD && !map.barrierE"}},{"type":"TouchTrigger","x":112,"y":296,"level":1,"settings":{"name":"","size":{"x":56,"y":8},"type":"WHILE_TOUCH_TRUE","zHeight":16,"reactToParty":false,"mapId":55,"variable":"tmp.barrierCEscape"}},{"type":"ScalableProp","x":256,"y":280,"level":1,"settings":{"name":"","size":{"x":8,"y":96},"patternOffset":{"x":0,"y":0},"timeOffset":0,"blockNavMap":false,"mapId":56,"propConfig":{"sheet":"final-dng-inner","name":"fenceV","ends":{"north":"NORTH_WEST","south":"SOUTH_WEST"}}}},{"type":"ScalableProp","x":312,"y":280,"level":1,"settings":{"name":"","size":{"x":8,"y":80},"patternOffset":{"x":0,"y":0},"timeOffset":0,"blockNavMap":false,"mapId":57,"propConfig":{"sheet":"final-dng-inner","name":"fenceV","ends":{"north":"NORTH_EAST","south":"SOUTH_EAST"}}}},{"type":"WallHorizontal","x":376,"y":344,"level":1,"settings":{"name":"","size":{"x":48,"y":8},"skipRender":false,"leftEnd":"STOP","rightEnd":"STOP","collType":"BLOCK","wallZHeight":24,"noNavMapBlock":false,"mapId":59,"condition":"!map.barrierE"}},{"type":"FloorSwitch","x":392,"y":248,"level":1,"settings":{"name":"","switchType":"PERMANENT","mapId":60,"variable":"map.barrierE"}},{"type":"GlowingLine","x":396,"y":268,"level":1,"settings":{"name":"","size":{"x":8,"y":72},"mapId":61,"condition":"map.barrierE"}},{"type":"GlowingLine","x":348,"y":252,"level":1,"settings":{"name":"","size":{"x":40,"y":8},"mapId":62,"condition":"map.barrierE"}},{"type":"GlowingLine","x":300,"y":252,"level":1,"settings":{"name":"","size":{"x":24,"y":8},"mapId":63,"condition":"map.barrierE || tmp.barrierD"}},{"type":"GlowingLine","x":284,"y":252,"level":1,"settings":{"name":"","size":{"x":8,"y":72},"mapId":64,"condition":"map.barrierE || tmp.barrierD"}},{"type":"GlowingLine","x":132,"y":380,"level":1,"settings":{"name":"","size":{"x":136,"y":8},"mapId":65,"condition":"tmp.barrierC"}},{"type":"GlowingLine","x":132,"y":316,"level":1,"settings":{"name":"","size":{"x":8,"y":56},"mapId":66,"condition":"tmp.barrierC"}},{"type":"GlowingLine","x":268,"y":388,"level":1,"settings":{"name":"","size":{"x":8,"y":8},"mapId":67,"condition":"tmp.barrierC"}},{"type":"GlowingLine","x":132,"y":396,"level":1,"settings":{"name":"","size":{"x":56,"y":8},"mapId":68,"condition":"tmp.barrierB"}},{"type":"GlowingLine","x":132,"y":412,"level":1,"settings":{"name":"","size":{"x":8,"y":56},"mapId":69,"condition":"tmp.barrierB"}},{"type":"Prop","x":656,"y":296,"level":1,"settings":{"name":"","mapId":70,"propType":{"sheet":"final-dng-inner","name":"slopeNWtop"},"propAnim":"","condAnims":[]}},{"type":"ScalableProp","x":560,"y":312,"level":1,"settings":{"name":"","size":{"x":96,"y":8},"patternOffset":{"x":0,"y":0},"timeOffset":0,"blockNavMap":false,"mapId":71,"propConfig":{"sheet":"final-dng-inner","name":"fenceH","ends":{"west":"","east":""}}}},{"type":"Prop","x":544,"y":296,"level":1,"settings":{"name":"","mapId":72,"propType":{"sheet":"final-dng-inner","name":"slopeNEtop"},"propAnim":"","condAnims":[]}},{"type":"ScalableProp","x":544,"y":280,"level":1,"settings":{"name":"","size":{"x":8,"y":16},"patternOffset":{"x":0,"y":0},"timeOffset":0,"blockNavMap":false,"mapId":73,"propConfig":{"sheet":"final-dng-inner","name":"fenceV","ends":{"north":"NORTH_WEST","south":"SOUTH_MIX"}}}},{"type":"ScalableProp","x":664,"y":240,"level":1,"settings":{"name":"","size":{"x":8,"y":56},"patternOffset":{"x":0,"y":0},"timeOffset":0,"blockNavMap":false,"mapId":74,"propConfig":{"sheet":"final-dng-inner","name":"fenceV","ends":{"north":"NORTH_END","south":"SOUTH_MIX"}}}},{"type":"GlowingLine","x":332,"y":400,"level":1,"settings":{"name":"","size":{"x":216,"y":8},"mapId":75,"condition":"map.barrierA"}},{"type":"GlowingLine","x":548,"y":408,"level":1,"settings":{"name":"","size":{"x":8,"y":8},"mapId":76,"condition":"map.barrierA"}},{"type":"ScalableProp","x":232,"y":276,"level":{"level":0,"offset":95},"settings":{"name":"","size":{"x":24,"y":4},"patternOffset":{"x":0,"y":0},"timeOffset":0,"blockNavMap":false,"mapId":77,"propConfig":{"sheet":"final-dng-glow","name":"fxShockH","ends":null}}},{"type":"ScalableProp","x":320,"y":276,"level":{"level":0,"offset":95},"settings":{"name":"","size":{"x":16,"y":4},"patternOffset":{"x":0,"y":0},"timeOffset":0,"blockNavMap":false,"mapId":78,"propConfig":{"sheet":"final-dng-glow","name":"fxShockH","ends":null}}},{"type":"EventTrigger","x":456,"y":520,"level":1,"settings":{"name":"FerroIntro","eventType":"CUTSCENE","endCondition":"map.ferroThere","event":[{"entity":{"player":true},"action":[{"type":"SET_RELATIVE_SPEED","value":0.3},{"target":{"x":400,"y":568,"lvl":"1"},"precise":true,"forceTime":false,"type":"MOVE_TO_POINT"}],"repeating":false,"wait":false,"keepState":false,"immediately":false,"type":"DO_ACTION"},{"pos":{"x":400,"y":452},"speed":"SLOW","transition":"EASE_IN_OUT","wait":true,"waitSkip":0.3,"zoom":1,"type":"SET_CAMERA_POS"},{"zoom":1.5,"duration":1.5,"transition":"EASE_IN_OUT","type":"SET_CAMERA_ZOOM"},{"changeType":"set","type":"CHANGE_VAR_BOOL","varName":"map.ferroThere","value":true},{"ignoreSlowDown":false,"type":"WAIT","time":1.5},{"speed":"NORMAL","transition":"EASE_IN_OUT","wait":false,"waitSkip":0,"type":"RESET_CAMERA"}],"triggerType":"ALWAYS","mapId":79,"startCondition":""}},{"type":"ConditionalLight","x":396,"y":452,"level":1,"settings":{"name":"","lightSize":"XXXL","glowSize":"XXL","weather":"","mapId":80,"condition":"map.ferroThere"}},{"type":"ElementPoleDest","x":392,"y":480,"level":1,"settings":{"name":"","group":"","element":"HEAT","activeTime":0,"mapId":81,"variable":""}},{"type":"ElementPoleDest","x":416,"y":456,"level":1,"settings":{"name":"","group":"","element":"SHOCK","activeTime":0,"mapId":82,"variable":""}},{"type":"ElementPoleDest","x":392,"y":432,"level":1,"settings":{"name":"","group":"","element":"COLD","activeTime":0,"mapId":83,"variable":""}},{"type":"ElementPoleDest","x":368,"y":456,"level":1,"settings":{"name":"","group":"","element":"WAVE","activeTime":0,"mapId":84,"variable":""}}],"layer":[{"id":13,"type":"Background","name":"Parallax","level":"first","width":49,"height":43,"visible":1,"tilesetName":"media\/map\/final-dungeon-inner.png","repeat":false,"lighter":false,"distance":1.1,"yDistance":0,"tilesize":16,"moveSpeed":{"x":0,"y":0},"data":[[614,614,614,614,614,614,614,614,614,614,614,614,614,614,614,614,614,614,614,614,614,614,614,614,614,614,614,614,614,614,614,614,614,614,614,614,614,614,614,614,614,614,614,614,614,614,0,0,0],[614,614,614,614,614,614,614,614,614,614,614,614,614,614,614,614,614,614,614,614,614,614,614,614,614,614,614,614,614,614,614,614,614,614,614,614,614,614,614,614,614,614,614,614,614,614,0,0,0],[614,614,614,614,614,614,614,614,614,614,614,614,614,614,614,614,614,614,614,614,614,614,614,614,614,614,614,614,614,614,614,614,614,614,614,614,614,614,614,614,614,614,614,614,614,614,0,0,0],[614,614,614,614,614,614,614,614,614,614,614,614,614,614,614,614,614,614,614,614,614,614,614,614,614,614,614,614,614,614,614,614,614,614,614,614,614,614,614,614,614,614,614,614,614,614,0,0,0],[614,614,614,614,614,614,614,614,614,614,614,614,614,614,614,614,614,614,614,614,614,614,614,614,614,614,614,614,614,614,614,614,614,614,614,614,614,614,614,614,614,614,614,614,614,614,0,0,0],[614,614,614,614,614,614,614,614,614,614,614,614,614,614,614,614,614,614,614,614,614,614,614,614,614,614,614,614,614,614,614,614,614,614,614,614,614,614,614,614,614,614,614,614,614,614,0,0,0],[614,614,614,614,614,614,614,614,614,614,614,614,614,614,614,614,614,614,614,614,614,614,614,614,614,614,614,614,614,614,614,614,614,614,614,614,614,614,614,614,614,614,614,614,614,614,0,0,0],[614,614,614,614,614,614,614,614,614,614,614,614,614,614,614,614,614,614,614,614,614,614,614,614,614,614,614,614,614,614,614,614,614,614,614,614,614,614,614,614,614,614,614,614,614,614,0,0,0],[614,614,614,614,614,614,614,614,614,614,614,614,614,614,614,614,614,614,614,614,614,614,614,614,614,614,614,614,614,614,614,614,614,614,614,614,614,614,614,614,614,614,614,614,614,614,0,0,0],[614,614,614,614,614,614,614,614,614,614,614,614,614,614,614,614,614,614,614,614,614,614,614,614,614,614,614,614,614,614,614,614,614,614,614,614,614,614,614,614,614,614,614,614,614,614,0,0,0],[614,614,614,614,614,614,614,614,614,614,614,614,614,614,614,614,614,614,614,614,614,614,614,614,614,614,614,614,614,614,614,614,614,614,614,614,614,614,614,614,614,614,614,614,614,614,0,0,0],[614,614,614,614,614,614,614,614,614,614,614,614,614,614,614,614,614,614,614,614,614,614,614,614,614,614,614,614,614,614,614,614,614,614,614,614,614,614,614,614,614,614,614,614,614,614,0,0,0],[614,614,614,614,614,614,614,614,614,614,614,614,614,614,614,614,614,614,614,614,614,614,614,614,614,614,614,614,614,614,614,614,614,614,614,614,614,614,614,614,614,614,614,614,614,614,0,0,0],[614,614,614,614,614,614,614,614,614,614,614,614,614,614,614,614,614,614,614,614,614,614,614,614,614,614,614,614,614,614,614,614,614,614,614,614,614,614,614,614,614,614,614,614,614,614,0,0,0],[614,614,614,614,614,614,614,614,614,614,614,614,614,614,614,614,614,614,614,614,614,614,614,614,614,614,614,614,614,614,614,614,614,614,614,614,614,614,614,614,614,614,614,614,614,614,0,0,0],[614,614,614,614,614,614,614,614,614,614,614,614,614,614,614,614,614,614,614,614,614,614,614,614,614,614,614,614,614,614,614,614,614,614,614,614,614,614,614,614,614,614,614,614,614,614,0,0,0],[614,614,614,614,614,614,614,614,614,614,614,614,614,614,614,614,614,614,614,614,614,614,614,614,614,614,614,614,614,614,614,614,614,614,614,614,614,614,614,614,614,614,614,614,614,614,0,0,0],[614,614,614,614,614,614,614,614,614,614,614,614,614,614,614,614,614,614,614,614,614,614,614,614,614,614,614,614,614,614,614,614,614,614,614,614,614,614,614,614,615,616,617,614,614,614,0,0,0],[614,614,614,614,614,614,614,614,614,614,614,614,614,614,614,614,614,614,614,614,614,614,614,614,614,614,614,614,614,614,614,614,614,614,614,614,614,614,614,615,647,648,649,617,614,614,0,0,0],[614,614,614,614,614,614,614,614,614,614,614,615,616,616,617,614,614,614,614,614,614,614,614,614,614,614,614,614,615,616,616,617,614,614,614,614,614,614,614,647,679,680,681,649,617,614,0,0,0],[614,614,614,614,614,614,614,614,614,614,615,647,648,648,649,614,614,614,614,614,614,614,614,614,614,614,614,615,647,648,648,649,617,614,614,614,614,614,614,679,711,712,713,681,649,614,0,0,0],[614,614,614,614,614,614,614,614,614,615,647,679,680,680,681,614,614,614,614,614,614,614,614,614,614,614,615,647,679,680,680,681,649,616,616,616,616,616,616,711,712,712,712,713,681,614,0,0,0],[614,614,614,614,614,614,614,614,614,647,679,711,712,712,713,614,614,614,614,614,614,614,614,614,614,614,647,679,711,712,712,713,681,648,648,648,648,648,648,712,712,712,712,712,713,614,0,0,0],[614,614,614,614,614,614,614,614,614,679,711,712,712,712,712,614,614,614,614,614,614,614,614,614,614,614,679,711,614,680,712,712,713,680,680,680,680,680,680,712,712,712,712,712,712,614,0,0,0],[614,614,614,614,614,614,614,614,614,712,712,712,712,712,712,614,614,614,614,614,614,614,614,614,614,614,711,614,614,712,712,712,712,712,712,712,712,712,712,712,712,712,712,712,712,614,0,0,0],[614,614,614,614,614,614,614,614,614,614,614,614,614,614,614,614,614,614,614,614,614,614,614,614,614,614,614,614,614,614,614,614,614,614,614,614,614,614,614,614,712,712,712,712,712,614,0,0,0],[614,614,614,614,614,614,614,614,614,614,614,614,614,614,614,614,614,614,614,614,614,614,614,614,614,614,614,614,614,614,614,614,614,614,614,614,614,614,614,614,712,712,712,712,712,614,0,0,0],[614,614,614,614,614,614,614,614,614,614,614,614,614,614,614,614,614,614,614,614,614,614,614,614,614,614,614,614,614,615,616,616,616,616,616,616,617,614,614,614,712,712,712,712,712,614,0,0,0],[614,614,614,614,614,614,614,614,614,614,614,615,616,616,616,616,616,617,614,614,614,614,614,614,614,614,614,614,615,647,648,648,648,648,648,648,649,617,614,614,712,712,712,712,712,614,0,0,0],[614,614,614,614,614,614,614,614,614,614,615,647,648,648,648,648,648,649,614,614,614,614,614,614,614,614,614,614,647,679,680,680,680,680,680,680,681,649,617,614,712,712,712,712,712,614,0,0,0],[614,614,614,614,614,614,614,614,614,615,647,679,680,680,680,680,680,681,614,614,614,614,614,614,614,614,614,614,679,711,712,712,712,712,712,712,713,681,649,614,712,712,712,712,712,614,0,0,0],[614,614,614,614,614,614,614,614,614,647,679,711,712,712,712,712,712,713,614,614,614,614,614,614,614,614,614,614,711,712,712,712,712,712,712,712,712,713,681,614,712,712,712,712,712,614,0,0,0],[614,614,614,614,614,614,614,614,614,679,711,712,712,712,712,712,712,712,614,614,614,614,614,614,614,614,614,614,712,712,712,712,712,712,712,712,712,712,713,614,712,712,712,712,712,614,0,0,0],[614,614,614,614,614,614,614,614,614,712,712,712,712,712,712,712,712,712,614,614,614,614,614,614,614,614,614,614,712,712,712,712,712,712,712,712,712,712,712,614,712,712,712,712,712,614,0,0,0],[614,614,614,614,614,614,614,614,614,614,614,614,614,614,614,614,614,614,614,614,614,614,614,614,614,614,614,614,614,614,614,614,614,614,614,712,712,712,712,614,712,712,712,712,614,614,0,0,0],[614,614,614,614,614,614,614,614,614,614,614,614,614,614,614,614,614,614,614,614,614,614,614,614,614,614,614,614,614,614,614,614,614,614,614,614,614,712,712,614,614,614,614,614,614,614,0,0,0],[614,614,614,614,614,614,614,614,614,614,614,614,614,614,614,614,614,614,614,614,614,614,614,614,614,614,0,0,0,0,0,0,0,0,0,0,0,0,0,0,614,614,614,614,614,614,0,0,0],[0,0,0,0,0,0,0,0,0,0,0,0,0,0,0,0,0,0,0,0,0,0,0,0,0,0,0,0,0,0,0,0,0,0,0,0,0,0,0,0,0,0,0,0,0,0,0,0,0],[0,0,0,0,0,0,0,0,0,0,0,0,0,0,0,0,0,0,0,0,0,0,0,0,0,0,0,0,0,0,0,0,0,0,0,0,0,0,0,0,0,0,0,0,0,0,0,0,0],[0,0,0,0,0,0,0,0,0,0,0,0,0,0,0,0,0,0,0,0,0,0,0,0,0,0,0,0,0,0,0,0,0,0,0,0,0,0,0,0,0,0,0,0,0,0,0,0,0],[0,0,0,0,0,0,0,0,0,0,0,0,0,0,0,0,0,0,0,0,0,0,0,0,0,0,0,0,0,0,0,0,0,0,0,0,0,0,0,0,0,0,0,0,0,0,0,0,0],[0,0,0,0,0,0,0,0,0,0,0,0,0,0,0,0,0,0,0,0,0,0,0,0,0,0,0,0,0,0,0,0,0,0,0,0,0,0,0,0,0,0,0,0,0,0,0,0,0],[0,0,0,0,0,0,0,0,0,0,0,0,0,0,0,0,0,0,0,0,0,0,0,0,0,0,0,0,0,0,0,0,0,0,0,0,0,0,0,0,0,0,0,0,0,0,0,0,0]]},{"id":0,"type":"Background","name":"Below","level":"0","width":50,"height":45,"visible":1,"tilesetName":"media\/map\/final-dungeon-inner.png","repeat":false,"distance":1,"yDistance":0,"tilesize":16,"moveSpeed":{"x":0,"y":0},"data":[[0,0,0,0,0,0,0,0,0,0,0,0,0,0,0,0,0,0,0,0,0,0,0,0,0,0,0,0,0,0,0,0,0,0,0,0,0,0,0,0,0,0,0,0,0,0,0,0,0,0],[0,0,0,0,0,0,0,0,0,0,0,0,0,0,0,0,0,0,0,0,0,0,0,0,0,0,0,0,0,0,0,0,0,0,0,0,0,0,0,0,0,0,0,0,0,0,0,0,0,0],[0,0,0,0,0,0,0,0,0,0,0,0,0,0,0,0,0,0,0,0,0,0,0,0,0,0,0,0,0,0,0,0,0,0,0,0,0,0,0,0,0,0,0,0,0,0,0,0,0,0],[0,0,0,0,0,0,0,0,0,0,0,0,0,0,0,0,0,0,0,0,0,0,0,0,0,0,0,0,0,0,0,0,0,0,0,0,0,0,0,0,0,0,0,0,0,0,0,0,0,0],[0,0,0,0,0,0,0,0,0,0,0,0,0,0,0,0,0,0,0,0,0,0,0,0,0,0,0,0,0,0,0,0,0,0,0,0,0,0,0,0,0,0,0,0,0,0,0,0,0,0],[0,0,0,0,0,0,0,0,0,0,0,0,0,0,0,0,0,0,0,0,0,0,0,0,0,0,0,0,0,0,0,0,0,0,0,0,0,0,0,0,0,0,0,0,0,0,0,0,0,0],[0,0,0,0,0,0,0,0,0,0,0,0,0,0,0,0,0,0,0,0,0,0,0,0,0,0,0,0,0,0,0,0,0,0,0,0,0,0,0,0,0,0,0,0,0,0,0,0,0,0],[0,0,0,0,0,0,0,0,0,0,0,0,0,0,0,0,0,0,0,0,0,0,0,0,0,0,0,0,0,0,0,0,0,0,0,0,0,0,0,0,0,0,0,0,0,0,0,0,0,0],[0,0,0,0,0,0,0,0,0,0,0,0,0,0,0,0,0,0,0,0,0,0,0,0,0,0,0,0,0,0,0,0,0,0,0,0,0,0,0,0,0,0,0,0,0,0,0,0,0,0],[0,0,0,0,0,0,0,0,0,0,0,0,0,0,0,0,0,0,0,0,0,0,0,0,0,0,0,0,0,0,0,0,0,0,0,0,0,0,0,0,0,0,0,0,0,0,0,0,0,0],[0,0,0,0,0,0,0,0,0,0,0,0,0,0,0,0,0,0,0,0,0,0,0,0,0,0,0,0,0,0,0,0,0,0,0,0,0,0,0,0,0,0,0,0,0,0,0,0,0,0],[0,0,0,0,0,0,0,0,0,0,0,0,0,0,0,0,0,0,0,0,0,0,0,0,0,0,0,0,0,0,0,0,0,0,0,0,0,0,0,0,0,0,0,0,0,0,0,0,0,0],[0,0,0,0,0,0,0,0,0,0,0,0,0,0,0,0,0,0,0,0,0,0,0,0,0,0,0,0,0,0,0,0,0,0,0,0,0,0,0,0,0,0,0,0,0,0,0,0,0,0],[0,0,0,0,0,0,0,0,0,0,0,0,0,0,0,0,0,0,0,0,0,0,0,0,0,0,0,0,0,0,0,0,0,0,0,0,0,0,0,0,0,0,0,0,0,0,0,0,0,0],[0,0,0,0,0,0,0,0,0,0,0,0,0,0,0,0,0,0,0,0,0,0,0,0,0,0,0,0,0,0,0,0,0,0,0,0,0,0,0,0,0,0,455,455,0,0,0,0,0,0],[0,0,0,0,0,0,0,0,0,0,0,0,0,0,0,0,0,0,0,0,0,0,0,0,0,0,0,0,0,0,0,0,0,0,0,0,0,0,0,0,0,0,487,487,490,0,0,0,0,0],[0,0,0,0,0,0,0,0,0,0,0,0,0,0,0,0,0,0,0,0,0,0,0,0,0,0,0,0,0,0,0,0,0,0,0,0,0,0,0,0,0,0,519,519,522,0,0,0,0,0],[0,0,0,0,0,0,0,0,0,0,0,0,0,0,0,0,0,0,0,0,0,0,0,0,0,0,0,0,0,0,0,0,0,0,0,0,0,0,0,0,0,0,0,0,554,0,0,0,0,0],[0,0,0,0,0,0,0,0,0,0,0,0,556,423,556,423,0,0,0,0,423,0,0,0,0,0,0,0,0,423,556,423,556,423,0,0,0,0,0,0,0,0,0,0,0,0,0,0,0,0],[0,0,0,0,0,0,0,0,0,0,0,425,620,487,620,487,0,0,0,0,487,591,0,0,0,0,0,0,590,487,620,487,620,487,0,0,0,0,0,0,487,0,0,0,0,0,0,0,0,0],[0,0,0,0,0,0,0,0,0,0,0,521,652,519,652,519,0,0,0,0,519,687,426,0,0,0,0,425,686,519,652,519,652,519,426,423,556,423,423,556,423,425,0,0,0,0,0,0,0,0],[0,0,0,0,0,0,0,0,0,0,0,553,0,0,0,0,0,0,0,0,0,719,522,0,0,0,0,521,718,0,0,0,0,0,522,487,620,487,487,620,487,521,0,0,0,0,0,0,0,0],[0,0,0,0,0,0,0,0,0,0,0,0,0,0,0,0,0,0,0,0,0,0,554,0,0,0,0,553,0,0,0,0,0,0,554,519,652,519,519,652,519,553,0,0,0,0,0,0,0,0],[0,0,0,0,0,0,0,0,0,0,0,0,0,0,0,0,0,0,0,0,0,0,0,0,0,0,0,0,0,0,0,0,0,0,0,0,0,0,0,0,0,0,0,0,0,0,0,0,0,0],[0,0,0,0,0,0,0,0,0,0,0,0,0,0,0,0,0,0,0,0,0,0,0,0,0,0,0,0,0,0,0,0,0,0,0,0,0,0,0,0,0,0,0,0,0,0,0,0,0,0],[0,0,0,0,0,0,0,0,0,0,0,0,0,0,0,0,0,0,0,0,0,0,0,0,0,0,0,0,0,0,0,0,0,0,0,0,0,0,0,0,0,0,0,0,0,0,0,0,0,0],[0,0,0,0,0,0,0,0,0,0,0,423,423,423,423,423,0,0,0,0,0,0,0,0,0,0,0,0,0,0,0,423,556,423,556,423,556,423,423,423,423,423,0,0,0,0,0,0,0,0],[0,0,0,0,0,0,0,0,0,0,0,423,556,423,556,423,556,423,556,423,0,0,0,0,0,0,0,0,0,0,425,487,620,487,620,487,620,487,426,426,426,426,426,0,0,0,0,0,0,0],[0,0,0,0,0,0,0,0,0,0,0,487,620,487,620,487,620,487,620,487,0,0,0,0,0,0,0,0,0,0,521,519,652,519,652,519,652,519,522,522,522,522,522,0,0,0,0,0,0,0],[0,0,0,0,0,0,0,0,0,0,0,519,652,519,652,519,652,519,652,519,0,0,0,0,0,0,0,0,0,0,553,0,0,0,0,0,0,0,554,554,0,0,554,0,0,0,0,0,0,0],[0,0,0,0,0,0,0,0,0,0,0,0,0,0,0,0,0,0,0,0,0,0,0,0,0,0,0,0,0,0,0,0,0,0,0,0,0,0,0,0,0,0,0,0,0,0,0,0,0,0],[0,0,0,0,0,0,0,0,0,0,0,0,0,0,0,0,0,0,0,0,0,0,0,0,0,0,0,0,0,0,0,0,0,426,423,425,0,0,0,0,0,0,0,0,0,0,0,0,0,0],[0,0,0,0,0,0,0,0,0,0,0,0,0,0,0,0,0,0,0,0,0,0,0,0,0,0,0,0,0,0,0,0,0,522,487,521,0,0,0,0,0,0,0,0,0,0,0,0,0,0],[0,0,0,0,0,0,0,0,0,0,0,0,0,0,0,0,0,0,0,0,0,0,0,0,0,0,0,0,0,0,0,0,0,554,519,553,0,0,0,0,0,0,0,0,0,0,0,0,0,0],[0,0,0,0,0,0,0,0,0,0,0,0,0,0,0,0,0,0,0,0,0,0,0,0,0,0,0,0,0,0,0,0,0,614,614,614,0,0,0,0,0,0,0,0,0,0,0,0,0,0],[0,0,0,0,0,0,0,0,0,0,0,0,0,0,0,0,0,0,0,0,0,0,0,0,0,0,0,0,0,0,0,0,0,614,614,614,0,0,0,0,0,0,0,0,0,0,0,0,0,0],[0,0,0,0,0,0,0,0,0,0,0,0,0,0,0,0,0,0,0,0,0,0,0,0,0,0,0,0,0,0,0,0,0,0,0,0,0,0,0,0,0,0,0,0,0,0,0,0,0,0],[0,0,0,0,0,0,0,0,0,0,0,0,0,0,0,0,0,0,0,0,0,0,0,0,0,0,0,0,0,0,0,0,0,0,0,0,0,0,0,0,0,0,0,0,0,0,0,0,0,0],[0,0,0,0,0,0,0,0,0,0,0,0,0,0,0,0,0,0,0,0,0,0,0,0,0,0,0,0,0,0,0,0,0,0,0,0,0,0,0,0,0,0,0,0,0,0,0,0,0,0],[0,0,0,0,0,0,0,0,0,0,0,0,0,0,0,0,0,0,0,0,0,0,0,0,0,0,0,0,0,0,0,0,0,0,0,0,0,0,0,0,0,0,0,0,0,0,0,0,0,0],[0,0,0,0,0,0,0,0,0,0,0,0,0,0,0,0,0,0,0,0,0,0,0,0,0,0,0,0,0,0,0,0,0,0,0,0,0,0,0,0,0,0,0,0,0,0,0,0,0,0],[0,0,0,0,0,0,0,0,0,0,0,0,0,0,0,0,0,0,0,0,0,0,0,0,0,0,0,0,0,0,0,0,0,0,0,0,0,0,0,0,0,0,0,0,0,0,0,0,0,0],[0,0,0,0,0,0,0,0,0,0,0,0,0,0,0,0,0,0,0,0,0,0,0,0,0,0,0,0,0,0,0,0,0,0,0,0,0,0,0,0,0,0,0,0,0,0,0,0,0,0],[0,0,0,0,0,0,0,0,0,0,0,0,0,0,0,0,0,0,0,0,0,0,0,0,0,0,0,0,0,0,0,0,0,0,0,0,0,0,0,0,0,0,0,0,0,0,0,0,0,0],[0,0,0,0,0,0,0,0,0,0,0,0,0,0,0,0,0,0,0,0,0,0,0,0,0,0,0,0,0,0,0,0,0,0,0,0,0,0,0,0,0,0,0,0,0,0,0,0,0,0]]},{"id":1,"type":"Background","name":"BelowDetails","level":"0","width":50,"height":45,"visible":1,"tilesetName":"media\/map\/final-dungeon-inner.png","repeat":false,"distance":1,"yDistance":0,"tilesize":16,"moveSpeed":{"x":0,"y":0},"data":[[0,0,0,0,0,0,0,0,0,0,0,0,0,0,0,0,0,0,0,0,0,0,0,0,0,0,0,0,0,0,0,0,0,0,0,0,0,0,0,0,0,0,0,0,0,0,0,0,0,0],[0,0,0,0,0,0,0,0,0,0,0,0,0,0,0,0,0,0,0,0,0,0,0,0,0,0,0,0,0,0,0,0,0,0,0,0,0,0,0,0,0,0,0,0,0,0,0,0,0,0],[0,0,0,0,0,0,0,0,0,0,0,0,0,0,0,0,0,0,0,0,0,0,0,0,0,0,0,0,0,0,0,0,0,0,0,0,0,0,0,0,0,0,0,0,0,0,0,0,0,0],[0,0,0,0,0,0,0,0,0,0,0,0,0,0,0,0,0,0,0,0,0,0,0,0,0,0,0,0,0,0,0,0,0,0,0,0,0,0,0,0,0,0,0,0,0,0,0,0,0,0],[0,0,0,0,0,0,0,0,0,0,0,0,0,0,0,0,0,0,0,0,0,0,0,0,0,0,0,0,0,0,0,0,0,0,0,0,0,0,0,0,0,0,0,0,0,0,0,0,0,0],[0,0,0,0,0,0,0,0,0,0,0,0,0,0,0,0,0,0,0,0,0,0,0,0,0,0,0,0,0,0,0,0,0,0,0,0,0,0,0,0,0,0,0,0,0,0,0,0,0,0],[0,0,0,0,0,0,0,0,0,0,0,0,0,0,0,0,0,0,0,0,0,0,0,0,0,0,0,0,0,0,0,0,0,0,0,0,0,0,0,0,0,0,0,0,0,0,0,0,0,0],[0,0,0,0,0,0,0,0,0,0,0,0,0,0,0,0,0,0,0,0,0,0,0,0,0,0,0,0,0,0,0,0,0,0,0,0,0,0,0,0,0,0,0,0,0,0,0,0,0,0],[0,0,0,0,0,0,0,0,0,0,0,0,0,0,0,0,0,0,0,0,0,0,0,0,0,0,0,0,0,0,0,0,0,0,0,0,0,0,0,0,0,0,0,0,0,0,0,0,0,0],[0,0,0,0,0,0,0,0,0,0,0,0,0,0,0,0,0,0,0,0,0,0,0,0,0,0,0,0,0,0,0,0,0,0,0,0,0,0,0,0,0,0,0,0,0,0,0,0,0,0],[0,0,0,0,0,0,0,0,0,0,0,0,0,0,0,0,0,0,0,0,0,0,0,0,0,0,0,0,0,0,0,0,0,0,0,0,0,0,0,0,0,0,0,0,0,0,0,0,0,0],[0,0,0,0,0,0,0,0,0,0,0,0,0,0,0,0,0,0,0,0,0,0,0,0,0,0,0,0,0,0,0,0,0,0,0,0,0,0,0,0,0,0,0,0,0,0,0,0,0,0],[0,0,0,0,0,0,0,0,0,0,0,0,0,0,0,0,0,0,0,0,0,0,0,0,0,0,0,0,0,0,0,0,0,0,0,0,0,0,0,0,0,0,0,0,0,0,0,0,0,0],[0,0,0,0,0,0,0,0,0,0,0,0,0,0,0,0,0,0,0,0,0,0,0,0,0,0,0,0,0,0,0,0,0,0,0,0,0,0,0,0,0,0,0,0,0,0,0,0,0,0],[0,0,0,0,0,0,0,0,0,0,0,0,0,0,0,0,0,0,0,0,0,0,0,0,0,0,0,0,0,0,0,0,0,0,0,0,0,0,0,0,0,0,0,0,0,0,0,0,0,0],[0,0,0,0,0,0,0,0,0,0,0,0,0,0,0,0,0,0,0,0,0,0,0,0,0,0,0,0,0,0,0,0,0,0,0,0,0,0,0,0,0,0,0,0,0,0,0,0,0,0],[0,0,0,0,0,0,0,0,0,0,0,0,0,0,0,0,0,0,0,0,0,0,0,0,0,0,0,0,0,0,0,0,0,0,0,0,0,0,0,0,0,0,0,0,0,0,0,0,0,0],[0,0,0,0,0,0,0,0,0,0,0,0,0,0,0,0,0,0,0,0,0,0,0,0,0,0,0,0,0,0,0,0,0,0,0,0,0,0,0,0,0,0,0,0,0,0,0,0,0,0],[0,0,0,0,0,0,0,0,0,0,0,0,0,0,0,0,0,0,0,0,0,0,0,0,0,0,0,0,0,0,0,0,0,0,0,0,0,0,0,0,0,0,0,0,0,0,0,0,0,0],[0,0,0,0,0,0,0,0,0,0,0,0,0,0,0,0,0,0,0,0,0,0,0,0,0,0,0,0,0,0,0,0,0,0,0,0,0,0,0,0,0,0,0,0,0,0,0,0,0,0],[0,0,0,0,0,0,0,0,0,0,0,0,0,0,0,0,0,0,0,0,0,0,0,0,0,0,0,0,0,0,0,0,0,0,0,0,0,0,0,0,0,0,0,0,0,0,0,0,0,0],[0,0,0,0,0,0,0,0,0,0,0,0,0,0,0,0,0,0,0,0,0,0,0,0,0,0,0,0,0,0,0,0,0,0,0,0,0,0,0,0,0,0,0,0,0,0,0,0,0,0],[0,0,0,0,0,0,0,0,0,0,0,0,0,0,0,0,0,0,0,0,0,0,0,0,0,0,0,0,0,0,0,0,0,0,0,0,0,0,0,0,0,0,0,0,0,0,0,0,0,0],[0,0,0,0,0,0,0,0,0,0,0,0,0,0,0,0,0,0,0,0,0,0,0,0,0,0,0,0,0,0,0,0,0,0,0,0,0,0,0,0,0,0,0,0,0,0,0,0,0,0],[0,0,0,0,0,0,0,0,0,0,0,0,0,0,0,0,0,0,0,0,0,0,0,0,0,0,0,0,0,0,0,0,0,0,0,0,0,0,0,0,0,0,0,0,0,0,0,0,0,0],[0,0,0,0,0,0,0,0,0,0,0,0,0,0,0,0,0,0,0,0,0,0,0,0,0,0,0,0,0,0,0,0,0,0,0,0,0,0,0,0,0,0,0,0,0,0,0,0,0,0],[0,0,0,0,0,0,0,0,0,0,0,0,0,0,0,0,0,0,0,0,0,0,0,0,0,0,0,0,0,0,0,0,0,0,0,0,0,0,0,0,0,0,0,0,0,0,0,0,0,0],[0,0,0,0,0,0,0,0,0,0,0,0,0,0,0,0,0,0,0,0,0,0,0,0,0,0,0,0,0,0,0,0,0,0,0,0,0,0,0,0,0,0,0,0,0,0,0,0,0,0],[0,0,0,0,0,0,0,0,0,0,0,0,0,0,0,0,0,0,0,0,0,0,0,0,0,0,0,0,0,0,0,0,0,0,0,0,0,0,0,0,0,0,0,0,0,0,0,0,0,0],[0,0,0,0,0,0,0,0,0,0,0,0,0,0,0,0,0,0,0,0,0,0,0,0,0,0,0,0,0,0,0,0,0,0,0,0,0,0,0,0,0,0,0,0,0,0,0,0,0,0],[0,0,0,0,0,0,0,0,0,0,0,0,0,0,0,0,0,0,0,0,0,0,0,0,0,0,0,0,0,0,0,0,0,0,0,0,0,0,0,0,0,0,0,0,0,0,0,0,0,0],[0,0,0,0,0,0,0,0,0,0,0,0,0,0,0,0,0,0,0,0,0,0,0,0,0,0,0,0,0,0,0,0,0,0,0,0,0,0,0,0,0,0,0,0,0,0,0,0,0,0],[0,0,0,0,0,0,0,0,0,0,0,0,0,0,0,0,0,0,0,0,0,0,0,0,0,0,0,0,0,0,0,0,0,0,0,0,0,0,0,0,0,0,0,0,0,0,0,0,0,0],[0,0,0,0,0,0,0,0,0,0,0,0,0,0,0,0,0,0,0,0,0,0,0,0,0,0,0,0,0,0,0,0,0,0,0,0,0,0,0,0,0,0,0,0,0,0,0,0,0,0],[0,0,0,0,0,0,0,0,0,0,0,0,0,0,0,0,0,0,0,0,0,0,0,0,0,0,0,0,0,0,0,0,0,0,0,0,0,0,0,0,0,0,0,0,0,0,0,0,0,0],[0,0,0,0,0,0,0,0,0,0,0,0,0,0,0,0,0,0,0,0,0,0,0,0,0,0,0,0,0,0,0,0,0,0,0,0,0,0,0,0,0,0,0,0,0,0,0,0,0,0],[0,0,0,0,0,0,0,0,0,0,0,0,0,0,0,0,0,0,0,0,0,0,0,0,0,0,0,0,0,0,0,0,0,0,0,0,0,0,0,0,0,0,0,0,0,0,0,0,0,0],[0,0,0,0,0,0,0,0,0,0,0,0,0,0,0,0,0,0,0,0,0,0,0,0,0,0,0,0,0,0,0,0,0,0,0,0,0,0,0,0,0,0,0,0,0,0,0,0,0,0],[0,0,0,0,0,0,0,0,0,0,0,0,0,0,0,0,0,0,0,0,0,0,0,0,0,0,0,0,0,0,0,0,0,0,0,0,0,0,0,0,0,0,0,0,0,0,0,0,0,0],[0,0,0,0,0,0,0,0,0,0,0,0,0,0,0,0,0,0,0,0,0,0,0,0,0,0,0,0,0,0,0,0,0,0,0,0,0,0,0,0,0,0,0,0,0,0,0,0,0,0],[0,0,0,0,0,0,0,0,0,0,0,0,0,0,0,0,0,0,0,0,0,0,0,0,0,0,0,0,0,0,0,0,0,0,0,0,0,0,0,0,0,0,0,0,0,0,0,0,0,0],[0,0,0,0,0,0,0,0,0,0,0,0,0,0,0,0,0,0,0,0,0,0,0,0,0,0,0,0,0,0,0,0,0,0,0,0,0,0,0,0,0,0,0,0,0,0,0,0,0,0],[0,0,0,0,0,0,0,0,0,0,0,0,0,0,0,0,0,0,0,0,0,0,0,0,0,0,0,0,0,0,0,0,0,0,0,0,0,0,0,0,0,0,0,0,0,0,0,0,0,0],[0,0,0,0,0,0,0,0,0,0,0,0,0,0,0,0,0,0,0,0,0,0,0,0,0,0,0,0,0,0,0,0,0,0,0,0,0,0,0,0,0,0,0,0,0,0,0,0,0,0],[0,0,0,0,0,0,0,0,0,0,0,0,0,0,0,0,0,0,0,0,0,0,0,0,0,0,0,0,0,0,0,0,0,0,0,0,0,0,0,0,0,0,0,0,0,0,0,0,0,0]]},{"id":2,"type":"Collision","name":"Collision","level":"0","width":50,"height":45,"visible":1,"tilesetName":"media\/map\/collisiontiles-16x16.png","repeat":false,"distance":1,"yDistance":0,"tilesize":16,"moveSpeed":{"x":0,"y":0},"data":[[0,0,0,0,0,0,0,0,0,0,0,0,0,0,0,0,0,0,0,0,0,0,0,0,0,0,0,0,0,0,0,0,0,0,0,0,0,0,0,0,0,0,0,0,0,0,0,0,0,0],[0,0,0,0,0,0,0,0,0,0,0,0,0,0,0,0,0,0,0,0,0,0,0,0,0,0,0,0,0,0,0,0,0,0,0,0,0,0,0,0,0,0,0,0,0,0,0,0,0,0],[0,0,0,0,0,0,0,0,0,0,0,0,0,0,0,0,0,0,0,0,0,0,0,0,0,0,0,0,0,0,0,0,0,0,0,0,0,0,0,0,0,0,0,0,0,0,0,0,0,0],[0,0,0,0,0,0,0,0,0,0,0,0,0,0,0,0,0,0,0,0,0,0,0,0,0,0,0,0,0,0,0,0,0,0,0,0,0,0,0,0,0,0,0,0,0,0,0,0,0,0],[0,0,0,0,0,0,0,0,0,0,0,0,0,0,0,0,0,0,0,0,0,0,0,0,0,0,0,0,0,0,0,0,0,0,0,0,0,0,0,0,0,0,0,0,0,0,0,0,0,0],[0,0,0,0,0,0,0,0,0,0,0,0,0,0,0,0,0,0,0,0,0,0,0,0,0,0,0,0,0,0,0,0,0,0,0,0,0,0,0,0,0,0,0,0,0,0,0,0,0,0],[0,0,0,0,0,0,0,0,0,0,0,0,0,0,0,0,0,0,0,0,0,0,0,0,0,0,0,0,0,0,0,0,0,0,0,0,0,0,0,0,0,0,0,0,0,0,0,0,0,0],[0,0,0,0,0,0,0,0,0,0,0,0,0,0,0,0,0,0,0,0,0,0,0,0,0,0,0,0,0,0,0,0,0,0,0,0,0,0,0,0,0,0,0,0,0,0,0,0,0,0],[0,0,0,0,0,0,0,0,0,0,0,0,0,0,0,0,0,0,0,0,0,0,0,0,0,0,0,0,0,0,0,0,0,0,0,0,0,0,0,0,0,0,0,0,0,0,0,0,0,0],[0,0,0,0,0,0,0,0,0,0,0,0,0,0,0,0,0,0,0,0,0,0,0,0,0,0,0,0,0,0,0,0,0,0,0,0,0,0,0,0,0,0,0,0,0,0,0,0,0,0],[0,0,0,0,0,0,0,0,0,0,0,0,0,0,0,0,0,0,0,0,0,0,0,0,0,0,0,0,0,0,0,0,0,0,0,0,0,0,0,0,0,0,0,0,0,0,0,0,0,0],[0,0,0,0,0,0,0,0,0,0,0,0,0,0,0,0,0,0,0,0,0,0,0,0,0,0,0,0,0,0,0,0,0,0,0,0,0,0,0,0,0,0,0,0,0,0,0,0,0,0],[0,0,0,0,0,0,0,0,0,0,0,0,0,0,0,0,0,0,0,0,0,0,0,0,0,0,0,0,0,0,0,0,0,0,0,0,0,0,0,0,0,0,0,0,0,0,0,0,0,0],[0,0,0,0,0,0,0,0,0,0,0,0,0,0,0,0,0,0,0,0,0,0,0,0,0,0,0,0,0,0,0,0,0,0,0,0,0,0,0,0,0,0,0,0,0,0,0,0,0,0],[0,0,0,0,0,0,0,0,0,0,0,0,0,0,0,0,0,0,0,0,0,0,0,0,0,0,0,0,0,0,0,0,0,0,0,0,0,0,0,0,0,0,0,0,0,0,0,0,0,0],[0,0,0,0,0,0,0,0,0,0,0,0,0,0,0,0,0,0,0,0,0,0,0,0,0,0,0,0,0,0,0,0,0,0,0,0,0,0,0,0,0,0,0,0,0,0,0,0,0,0],[0,0,0,0,0,0,0,0,0,0,0,0,0,0,0,0,0,0,0,0,0,0,0,0,0,0,0,0,0,0,0,0,0,0,0,0,0,0,0,0,0,0,0,0,0,0,0,0,0,0],[0,0,0,0,0,0,0,0,0,0,0,0,0,0,0,0,0,0,0,0,0,0,0,0,0,0,0,0,0,0,0,0,0,0,0,0,0,0,0,0,0,0,0,0,0,0,0,0,0,0],[0,0,0,0,0,0,0,0,0,0,0,0,0,0,0,0,0,0,0,0,0,0,0,0,0,0,0,0,0,0,0,0,0,0,0,0,0,0,0,0,0,0,0,0,0,0,0,0,0,0],[0,0,0,0,0,0,0,0,0,0,0,0,0,0,0,0,0,0,0,0,0,0,0,0,0,0,0,0,0,0,0,0,0,0,0,0,0,0,0,0,0,0,0,0,0,0,0,0,0,0],[0,0,0,0,0,0,0,0,0,0,0,0,0,0,0,0,0,0,0,0,0,0,0,0,0,0,0,0,0,0,0,0,0,0,0,0,0,0,0,0,0,0,1,1,4,0,0,0,0,0],[0,0,0,0,0,0,0,0,0,0,0,0,0,0,0,0,0,0,0,0,0,0,0,0,0,0,0,0,0,0,0,0,0,0,0,0,0,0,0,0,0,0,1,1,1,0,0,0,0,0],[0,0,0,0,0,0,0,0,0,0,0,0,0,0,0,0,0,0,0,0,0,0,0,0,0,0,0,0,0,0,0,0,0,0,0,0,0,0,0,0,0,0,1,1,1,0,0,0,0,0],[0,0,0,0,0,0,0,0,0,0,0,0,0,0,0,0,0,0,0,0,0,0,0,0,0,0,0,0,0,0,0,0,0,0,0,0,0,0,0,0,0,0,1,1,1,0,0,0,0,0],[0,0,0,0,0,0,0,0,0,0,0,7,1,1,1,1,0,0,0,0,1,4,0,0,0,0,0,0,7,1,1,1,1,1,0,0,0,0,0,0,0,0,1,1,1,0,0,0,0,0],[0,0,0,0,0,0,0,0,0,0,0,1,1,1,1,1,0,0,0,0,1,1,4,0,0,0,0,7,1,1,1,1,1,1,4,0,0,0,0,0,0,7,1,1,1,0,0,0,0,0],[0,0,0,0,0,0,0,0,0,0,0,1,1,1,1,1,0,0,0,0,1,1,1,0,0,0,0,1,1,1,1,1,1,1,1,1,1,1,1,1,1,1,1,1,1,0,0,0,0,0],[0,0,0,0,0,0,0,0,0,0,0,1,1,1,1,1,0,0,0,0,1,1,1,0,0,0,0,1,1,1,1,1,1,1,1,1,1,1,1,1,1,1,1,1,1,0,0,0,0,0],[0,0,0,0,0,0,0,0,0,0,0,1,1,1,1,1,0,0,0,0,0,0,0,0,0,0,0,6,1,1,1,1,1,1,1,1,1,1,1,1,1,1,1,1,1,0,0,0,0,0],[0,0,0,0,0,0,0,0,0,0,0,0,0,0,0,0,0,0,0,0,0,0,0,0,0,0,0,0,0,0,0,0,0,0,0,0,0,0,0,0,0,6,1,1,1,0,0,0,0,0],[0,0,0,0,0,0,0,0,0,0,0,0,0,0,0,0,0,0,0,0,0,0,0,0,0,0,0,0,0,0,0,0,0,0,0,0,0,0,0,0,0,0,6,1,1,0,0,0,0,0],[0,0,0,0,0,0,0,0,0,0,0,0,0,0,0,0,0,0,0,0,0,0,0,0,0,0,0,0,0,0,0,0,0,0,0,0,0,0,0,0,0,0,0,1,1,0,0,0,0,0],[0,0,0,0,0,0,0,0,0,0,0,0,0,0,0,0,0,0,0,0,0,0,0,0,0,0,0,0,0,0,7,1,1,1,1,1,1,1,4,0,0,0,0,1,1,0,0,0,0,0],[0,0,0,0,0,0,0,0,0,0,0,1,1,1,1,1,1,1,1,1,0,0,0,0,0,0,0,0,0,0,1,1,1,1,1,1,1,1,1,0,0,0,0,1,1,0,0,0,0,0],[0,0,0,0,0,0,0,0,0,0,0,1,1,1,1,1,1,1,1,1,0,0,0,0,0,0,0,0,0,0,1,1,1,5,0,6,1,1,1,0,0,0,0,1,1,0,0,0,0,0],[0,0,0,0,0,0,0,0,0,0,0,1,1,1,1,1,1,1,1,1,0,0,0,0,0,0,0,0,0,0,1,1,1,0,0,0,1,1,1,0,0,0,0,1,1,0,0,0,0,0],[0,0,0,0,0,0,0,0,0,0,0,6,1,1,1,1,1,1,1,1,0,0,0,0,0,0,0,0,0,0,1,1,1,4,0,7,1,1,1,0,0,0,0,1,1,0,0,0,0,0],[0,0,0,0,0,0,0,0,0,0,0,0,0,0,0,0,0,0,0,0,0,0,0,0,0,0,0,0,0,0,1,1,1,1,1,1,1,1,1,0,0,0,0,1,1,0,0,0,0,0],[0,0,0,0,0,0,0,0,0,0,0,0,0,0,0,0,0,0,0,0,0,0,0,0,0,0,0,0,0,0,6,1,1,1,1,1,1,1,5,0,0,0,0,1,1,0,0,0,0,0],[0,0,0,0,0,0,0,0,0,0,0,0,0,0,0,0,0,0,0,0,0,0,0,0,0,0,0,0,0,0,0,0,0,0,0,0,0,0,0,0,0,0,0,1,1,0,0,0,0,0],[0,0,0,0,0,0,0,0,0,0,0,0,0,0,0,0,0,0,0,0,0,0,0,0,0,0,0,0,0,0,0,0,0,0,0,0,0,0,0,0,0,0,0,1,1,0,0,0,0,0],[0,0,0,0,0,0,0,0,0,0,0,0,0,0,0,0,0,0,0,0,0,0,0,0,0,0,0,0,0,0,0,0,0,0,0,0,0,0,0,0,0,0,0,1,5,0,0,0,0,0],[0,0,0,0,0,0,0,0,0,0,0,0,0,0,0,0,0,0,0,0,0,0,0,0,0,0,0,0,0,0,0,0,0,0,0,0,0,0,0,0,0,0,0,0,0,0,0,0,0,0],[0,0,0,0,0,0,0,0,0,0,0,0,0,0,0,0,0,0,0,0,0,0,0,0,0,0,0,0,0,0,0,0,0,0,0,0,0,0,0,0,0,0,0,0,0,0,0,0,0,0],[0,0,0,0,0,0,0,0,0,0,0,0,0,0,0,0,0,0,0,0,0,0,0,0,0,0,0,0,0,0,0,0,0,0,0,0,0,0,0,0,0,0,0,0,0,0,0,0,0,0]]},{"id":3,"type":"Background","name":"Ground","level":"1","width":50,"height":45,"visible":1,"tilesetName":"media\/map\/final-dungeon-inner.png","repeat":false,"distance":1,"yDistance":0,"tilesize":16,"moveSpeed":{"x":0,"y":0},"data":[[167,167,167,167,167,167,167,167,167,167,167,167,167,167,167,167,167,167,167,167,167,167,167,167,167,167,167,167,167,167,167,167,167,167,167,167,167,167,167,167,167,167,167,167,167,167,167,167,167,167],[167,167,167,167,167,167,167,167,167,167,167,167,167,167,167,167,167,167,167,167,167,167,167,167,167,167,167,167,167,167,167,167,167,167,167,167,167,167,167,167,167,167,167,167,167,167,167,167,167,167],[167,167,167,167,167,167,167,167,167,167,167,167,167,167,167,167,167,167,167,167,167,167,167,167,167,167,167,167,167,167,167,167,167,167,167,167,167,167,167,167,167,167,167,167,167,167,167,167,167,167],[167,167,167,167,167,167,167,167,167,167,167,167,167,167,167,167,167,167,167,167,167,167,167,167,167,167,167,167,167,167,167,167,167,167,167,167,167,167,167,167,167,167,167,167,167,167,167,167,167,167],[167,167,167,167,167,167,167,167,167,167,167,167,167,167,167,167,167,167,167,167,167,167,167,167,167,167,167,167,167,167,167,167,167,167,167,167,167,167,167,167,167,167,167,167,167,167,167,167,167,167],[167,167,167,167,167,167,167,167,167,167,167,167,167,167,167,167,167,167,167,167,167,167,167,167,167,167,167,167,167,167,167,167,167,167,167,200,231,231,231,231,198,167,167,167,167,167,167,167,167,167],[167,167,167,167,167,167,167,167,167,167,167,167,167,167,167,167,167,167,167,167,167,167,167,167,167,167,167,167,167,167,167,167,167,167,200,232,263,263,263,263,230,198,167,167,167,167,167,167,167,167],[167,167,167,167,167,167,167,200,231,231,231,231,231,231,231,231,231,231,231,231,231,231,231,231,231,231,231,231,231,231,231,231,231,231,202,264,290,290,290,290,262,201,231,231,198,167,167,167,167,167],[167,167,167,167,167,167,200,232,263,263,263,263,263,263,263,263,263,263,263,263,263,263,263,263,263,263,263,263,263,263,263,263,263,263,234,291,322,322,322,322,289,233,263,263,230,198,167,167,167,167],[167,167,167,167,167,167,138,264,290,290,290,290,290,290,290,290,290,290,290,290,290,290,290,290,290,290,290,290,290,290,290,290,290,290,261,323,290,167,167,290,321,260,290,290,262,137,167,167,167,167],[167,167,167,167,167,167,138,291,322,322,322,322,322,322,322,322,322,322,322,322,322,322,322,322,322,322,322,322,322,322,322,322,322,322,293,291,322,167,167,322,289,292,322,322,289,137,167,167,167,167],[167,167,167,167,167,167,138,323,290,290,290,290,290,290,290,290,290,290,290,290,290,290,290,290,290,290,290,290,290,290,290,290,290,290,261,323,354,167,167,354,321,260,290,290,321,137,167,167,167,167],[167,167,167,167,167,167,138,291,322,322,322,322,322,322,322,322,322,322,322,322,322,322,322,322,322,322,322,322,322,322,322,322,322,322,293,355,7,2,2,39,353,292,322,322,289,137,167,167,167,167],[167,167,167,167,167,167,138,323,354,354,354,354,354,354,354,354,354,354,354,354,354,354,354,354,354,354,354,354,354,354,354,354,354,354,325,1,7,2,2,39,1,324,354,354,321,137,167,167,167,167],[167,167,167,167,167,167,170,355,1,1,1,1,1,1,1,1,7,2,2,39,1,1,1,7,2,2,39,1,1,1,1,1,1,1,1,1,7,2,2,39,1,165,0,0,458,169,167,167,167,167],[167,167,167,167,167,167,167,1,1,1,1,1,1,1,1,1,7,2,2,39,1,1,8,3,2,2,4,9,1,1,1,1,1,1,1,1,7,2,2,39,1,165,0,0,0,582,167,167,167,167],[167,167,167,167,167,167,167,1,1,1,1,1,1,1,1,1,7,2,2,39,1,1,40,35,2,2,36,41,1,1,1,1,1,1,1,1,40,35,36,41,1,165,0,0,0,582,167,167,167,167],[167,167,167,167,167,167,167,1,1,1,1,195,226,226,226,226,203,2,2,205,226,193,1,40,35,36,41,1,195,226,226,226,226,226,193,1,1,40,41,1,1,165,0,0,0,582,167,167,167,167],[167,167,167,167,167,167,167,1,1,1,195,393,0,0,0,0,174,2,2,175,0,559,193,1,40,41,1,195,558,0,0,0,0,0,164,1,1,1,1,1,1,165,0,0,0,582,167,167,167,167],[167,167,167,167,167,167,167,1,1,1,165,0,0,0,0,0,174,2,2,175,0,0,394,193,1,1,195,393,0,0,0,0,0,0,394,226,226,226,226,226,226,393,0,0,0,582,167,167,167,167],[167,167,167,167,167,167,167,1,1,1,165,0,0,0,0,0,174,2,2,175,0,0,0,164,1,1,165,0,0,0,0,0,0,0,0,0,0,0,0,0,0,0,0,0,0,582,167,167,167,167],[167,167,167,167,167,167,167,1,1,1,165,0,0,0,0,0,174,2,2,175,0,0,0,164,1,1,165,0,0,0,0,0,0,0,0,0,0,0,0,0,0,0,0,0,0,582,167,167,167,167],[167,167,167,167,167,167,167,6,6,9,165,0,0,0,0,0,174,2,2,173,130,130,130,161,1,1,163,131,0,0,0,0,0,0,0,0,0,0,0,0,0,0,0,0,0,582,167,167,167,167],[167,167,167,167,167,167,167,2,2,4,173,140,140,140,140,140,171,2,2,4,9,1,1,1,1,1,1,163,130,130,130,130,130,130,130,130,130,130,130,130,130,131,0,0,0,582,167,167,167,167],[167,167,167,167,167,167,167,2,2,2,2,2,2,2,2,2,2,2,2,2,4,9,1,1,1,1,1,1,1,1,1,1,1,1,1,1,1,1,1,1,1,163,131,0,0,582,167,167,167,167],[167,167,167,167,167,167,167,2,2,2,2,2,2,2,2,2,2,2,2,2,36,41,1,1,1,1,1,1,1,1,195,226,226,226,226,226,226,226,193,1,1,1,165,0,0,582,167,167,167,167],[167,167,167,167,167,167,167,2,2,36,205,236,236,236,236,236,236,236,236,236,203,1,1,1,8,9,1,1,1,195,393,0,0,0,0,0,0,0,394,193,1,1,165,0,0,582,167,167,167,167],[167,167,167,167,167,167,167,38,38,41,165,0,0,0,0,0,0,0,0,0,164,1,1,8,3,4,9,1,1,165,0,0,0,0,0,0,0,0,0,164,1,1,165,0,0,582,167,167,167,167],[167,167,167,167,167,167,167,1,1,1,165,0,0,0,0,0,0,0,0,0,164,1,8,3,2,2,4,9,1,165,0,0,0,129,130,131,0,0,0,164,1,1,165,0,0,582,167,167,167,167],[167,167,167,167,167,167,167,1,1,1,165,0,0,0,0,0,0,0,0,0,164,1,40,35,2,2,36,41,1,165,0,0,0,164,1,165,0,0,0,164,1,1,165,0,0,582,167,167,167,167],[167,167,167,167,167,167,167,1,1,1,163,131,0,0,0,0,0,0,0,0,164,1,1,40,35,36,41,1,1,165,0,0,0,394,226,393,0,0,0,164,1,1,165,0,0,582,167,167,167,167],[167,167,167,167,167,167,167,1,1,1,1,163,130,130,130,130,130,130,130,130,161,1,1,1,40,41,1,1,1,165,0,0,0,0,0,0,0,0,0,164,1,1,165,0,0,582,167,167,167,167],[167,167,167,167,167,167,167,1,1,1,1,1,1,1,1,1,1,1,1,1,1,1,1,1,1,1,1,1,1,163,131,0,0,0,0,0,0,0,129,161,1,1,165,0,0,582,167,167,167,167],[167,167,167,167,167,167,167,1,1,1,1,1,1,1,1,1,1,1,1,1,1,1,1,1,1,1,1,1,1,1,163,130,130,130,130,130,130,130,161,1,1,1,165,0,0,582,167,167,167,167],[167,167,167,167,167,167,167,1,1,1,1,1,1,1,1,1,1,1,1,1,1,1,1,1,1,1,1,1,1,1,1,1,1,1,1,1,1,1,1,1,1,1,165,0,0,582,167,167,167,167],[167,167,167,167,167,167,167,136,1,1,1,1,1,1,1,1,1,1,1,1,1,1,1,1,8,9,1,1,1,1,1,1,1,1,1,1,1,1,1,1,1,1,165,0,550,552,167,167,167,167],[167,167,167,167,167,167,167,168,135,135,135,135,135,135,135,135,135,135,135,135,136,1,1,8,3,4,9,1,1,134,135,135,135,135,135,135,135,135,135,135,135,135,135,585,552,167,167,167,167,167],[167,167,167,167,167,167,167,167,167,167,167,167,167,167,167,167,167,167,167,167,167,1,1,7,2,2,39,1,1,167,167,167,167,167,167,167,167,167,167,167,167,167,167,167,167,167,167,167,167,167],[167,167,167,167,167,167,167,167,167,167,167,167,167,167,167,167,167,167,167,167,167,1,1,7,2,2,39,1,1,167,167,167,167,167,167,167,167,167,167,167,167,167,167,167,167,167,167,167,167,167],[167,167,167,167,167,167,167,167,167,167,167,167,167,167,167,167,167,167,167,167,167,136,1,7,2,2,39,1,134,167,167,167,167,167,167,167,167,167,167,167,167,167,167,167,167,167,167,167,167,167],[167,167,167,167,167,167,167,167,167,167,167,167,167,167,167,167,167,167,167,167,167,168,135,135,135,135,135,135,166,167,167,167,167,167,167,167,167,167,167,167,167,167,167,167,167,167,167,167,167,167],[167,167,167,167,167,167,167,167,167,167,167,167,167,167,167,167,167,167,167,167,167,167,167,167,167,167,167,167,167,167,167,167,167,167,167,167,167,167,167,167,167,167,167,167,167,167,167,167,167,167],[167,167,167,167,167,167,167,167,167,167,167,167,167,167,167,167,167,167,167,167,167,167,167,167,167,167,167,167,167,167,167,167,167,167,167,167,167,167,167,167,167,167,167,167,167,167,167,167,167,167],[167,167,167,167,167,167,167,167,167,167,167,167,167,167,167,167,167,167,167,167,167,167,167,167,167,167,167,167,167,167,167,167,167,167,167,167,167,167,167,167,167,167,167,167,167,167,167,167,167,167],[167,167,167,167,167,167,167,167,167,167,167,167,167,167,167,167,167,167,167,167,167,167,167,167,167,167,167,167,167,167,167,167,167,167,167,167,167,167,167,167,167,167,167,167,167,167,167,167,167,167]]},{"id":4,"type":"Background","name":"GroundDetails","level":"1","width":50,"height":45,"visible":1,"tilesetName":"media\/map\/final-dungeon-inner.png","repeat":false,"distance":1,"yDistance":0,"tilesize":16,"moveSpeed":{"x":0,"y":0},"data":[[0,0,0,0,0,0,0,0,0,0,0,0,0,0,0,0,0,0,0,0,0,0,0,0,0,0,0,0,0,0,0,0,0,0,0,0,0,0,0,0,0,0,0,0,0,0,0,0,0,0],[0,0,0,0,0,0,0,0,0,0,0,0,0,0,0,0,0,0,0,0,0,0,0,0,0,0,0,0,0,0,0,0,0,0,0,0,0,0,0,0,0,0,0,0,0,0,0,0,0,0],[0,0,0,0,0,0,0,0,0,0,0,0,0,0,0,0,0,0,0,0,0,0,0,0,0,0,0,0,0,0,0,0,0,0,0,0,0,0,0,0,0,0,0,0,0,0,0,0,0,0],[0,0,0,0,0,0,0,0,0,0,0,0,0,0,0,0,0,0,0,0,0,0,0,0,0,0,0,0,0,0,0,0,0,0,0,0,0,0,0,0,0,0,0,0,0,0,0,0,0,0],[0,0,0,0,0,0,0,0,0,0,0,0,0,0,0,0,0,0,0,0,0,0,0,0,0,0,0,0,0,0,0,0,0,0,0,0,0,0,0,0,0,0,0,0,0,0,0,0,0,0],[0,0,0,0,0,0,0,0,0,0,0,0,0,0,0,0,0,0,0,0,0,0,0,0,0,0,0,0,0,0,0,0,0,0,0,0,278,278,278,278,0,0,0,0,0,0,0,0,0,0],[0,0,0,0,0,0,0,0,0,0,0,0,0,0,0,0,0,0,0,0,0,0,0,0,0,0,0,0,0,0,0,0,0,0,0,0,282,440,440,281,0,0,0,0,0,0,0,0,0,0],[0,0,0,0,0,0,0,0,0,0,0,0,310,310,0,0,0,0,0,0,0,278,278,310,310,310,310,278,278,0,0,0,0,0,0,0,317,441,409,349,0,0,0,0,0,0,0,0,0,0],[0,0,0,0,0,0,0,0,406,439,0,0,374,374,0,0,406,439,0,0,406,413,413,349,374,374,317,445,445,439,0,0,406,439,0,0,342,0,0,342,0,0,406,439,0,0,0,0,0,0],[0,0,0,0,0,0,0,0,440,440,0,0,314,313,0,0,440,440,0,0,281,440,440,374,314,313,374,440,440,282,0,0,440,440,0,0,313,0,0,314,0,0,440,440,0,0,0,0,0,0],[0,0,0,0,0,0,0,0,253,253,0,0,253,253,0,0,253,253,0,0,342,253,253,342,253,253,342,253,253,342,0,0,253,253,0,0,253,0,0,253,0,0,253,253,0,0,0,0,0,0],[0,0,0,0,0,0,0,0,440,440,0,0,440,440,0,0,440,440,0,406,285,413,413,349,282,281,317,445,445,285,439,0,440,440,0,0,440,0,0,440,0,0,440,440,0,0,0,0,0,0],[0,0,0,0,0,0,0,0,253,253,0,0,253,253,0,0,253,253,0,253,342,253,253,342,342,342,342,253,253,342,253,0,253,253,0,470,505,0,0,473,503,0,253,253,0,0,0,0,0,0],[0,0,0,0,0,0,0,0,438,407,0,0,282,281,0,0,438,407,0,440,374,440,440,314,374,374,313,440,440,374,440,0,438,407,0,474,471,0,0,502,506,0,438,407,0,0,0,0,0,0],[0,0,0,0,0,0,0,0,0,504,0,381,0,0,381,0,504,0,0,0,381,0,470,471,470,503,502,503,0,381,0,0,0,0,381,504,0,0,0,0,504,0,0,0,0,0,0,0,0,0],[0,0,0,0,0,0,0,0,470,471,0,502,472,472,471,0,502,472,472,472,475,472,471,470,471,502,503,502,472,475,472,472,472,472,471,473,503,0,0,470,505,0,0,0,0,0,0,0,0,0],[0,0,0,0,0,0,0,472,471,0,0,0,0,0,0,0,0,470,503,0,0,472,503,502,503,470,471,470,472,0,0,0,0,0,0,502,506,0,0,474,471,0,0,0,0,0,0,0,0,0],[0,0,0,0,0,0,0,0,0,0,0,0,0,0,0,0,470,471,502,503,0,0,502,503,502,471,470,471,471,0,0,0,0,0,0,0,502,503,470,471,0,0,0,0,0,0,0,0,0,0],[0,0,0,0,0,0,0,0,0,0,0,0,0,0,0,0,502,503,470,471,0,0,0,502,503,470,471,0,0,0,0,0,0,0,0,0,0,502,471,0,0,0,0,0,0,0,0,0,0,0],[0,0,0,0,0,0,0,0,0,0,0,0,0,0,0,0,0,504,504,0,0,0,0,0,504,504,0,0,0,0,0,0,0,0,0,0,0,0,0,0,0,0,0,0,0,0,0,0,0,0],[0,0,0,0,0,0,0,0,0,0,0,0,0,0,0,0,470,471,502,503,0,0,0,0,502,471,0,0,0,0,0,0,0,0,0,0,0,0,0,0,0,0,0,0,0,0,0,0,0,0],[0,0,0,0,0,0,0,503,0,0,0,0,0,0,0,0,504,0,0,504,0,0,0,0,0,0,0,0,0,0,0,0,0,0,0,0,0,0,0,0,0,0,0,0,0,0,0,0,0,0],[0,0,0,0,0,0,0,504,0,0,0,0,0,0,0,0,502,503,470,471,0,0,0,0,0,0,0,0,0,0,0,0,0,0,0,0,0,0,0,0,0,0,0,0,0,0,0,0,0,0],[0,0,0,0,0,0,0,504,0,0,0,0,0,0,0,0,0,504,504,0,0,0,0,0,470,503,0,0,0,0,504,0,0,0,0,0,0,0,504,0,504,0,0,0,0,0,0,0,0,0],[0,0,0,0,0,0,0,502,472,472,472,472,511,472,472,472,472,471,502,503,0,0,0,0,478,479,0,0,0,0,502,472,472,472,472,472,472,472,471,0,502,503,0,0,0,0,0,0,0,0],[0,0,0,0,0,0,0,470,472,472,472,472,510,472,472,472,472,503,470,471,0,0,0,0,504,504,0,0,0,0,0,0,0,0,0,0,0,0,0,0,0,502,472,0,0,0,0,0,0,0],[0,0,0,0,0,0,0,504,0,0,0,0,0,0,0,0,0,502,471,0,0,0,0,0,504,504,0,0,0,0,0,0,0,0,0,0,0,0,0,0,0,0,0,0,0,0,0,0,0,0],[0,0,0,0,0,0,0,504,0,0,0,0,0,0,0,0,0,0,0,0,0,0,0,470,471,502,503,0,0,0,0,0,0,0,0,0,0,0,0,536,503,470,537,0,0,0,0,0,0,0],[0,0,0,0,0,0,0,471,0,0,0,0,0,0,0,0,0,0,0,0,0,470,472,471,0,0,502,472,503,0,0,0,0,0,0,0,0,0,0,0,504,504,0,0,0,0,0,0,0,0],[0,0,0,0,0,0,0,0,0,0,0,0,0,0,0,0,0,0,0,0,0,502,472,503,0,0,470,472,471,0,0,0,0,0,0,0,0,0,0,0,504,504,0,0,0,0,0,0,0,0],[0,0,0,0,0,0,0,0,0,0,0,0,0,0,0,0,0,0,0,0,0,0,0,502,503,470,471,0,0,0,0,0,0,0,0,0,0,0,0,0,504,504,0,0,0,0,0,0,0,0],[0,0,0,0,0,0,0,0,0,0,0,0,504,0,0,0,0,0,0,504,0,0,0,0,504,504,0,0,0,0,0,0,0,0,0,0,0,0,0,536,471,502,537,0,0,0,0,0,0,0],[0,0,0,0,0,0,0,0,0,0,0,0,502,472,472,472,472,472,472,471,0,0,0,0,504,504,0,0,0,0,0,0,0,0,0,0,0,0,0,0,0,0,0,0,0,0,0,0,0,0],[0,0,0,0,0,0,0,472,503,0,0,0,0,0,0,0,0,0,0,0,0,0,0,0,478,479,0,0,0,0,0,0,0,0,0,0,0,0,0,0,0,470,472,0,0,0,0,0,0,0],[0,0,0,0,0,0,0,0,502,503,0,470,472,472,472,472,503,0,470,472,472,503,0,0,502,471,0,0,470,472,472,503,0,470,472,472,472,472,503,0,470,471,0,0,0,0,0,0,0,0],[0,0,0,0,0,0,0,0,0,504,0,504,0,0,0,0,504,0,504,0,0,502,503,0,470,503,0,470,471,0,0,504,0,504,0,0,0,0,504,0,504,0,0,0,0,0,0,0,0,0],[0,0,0,0,0,0,0,0,0,0,0,0,0,0,0,0,0,0,0,0,0,0,504,470,477,509,503,504,0,0,0,0,0,0,0,0,0,0,0,0,0,0,0,0,0,0,0,0,0,0],[0,0,0,0,0,0,0,0,0,0,0,0,0,0,0,0,0,0,0,0,0,0,504,504,478,479,504,504,0,0,0,0,0,0,0,0,0,0,0,0,0,0,0,0,0,0,0,0,0,0],[0,0,0,0,0,0,0,0,0,0,0,0,0,0,0,0,0,0,0,0,0,0,504,504,502,471,504,504,0,0,0,0,0,0,0,0,0,0,0,0,0,0,0,0,0,0,0,0,0,0],[0,0,0,0,0,0,0,0,0,0,0,0,0,0,0,0,0,0,0,0,0,0,504,504,0,0,504,504,0,0,0,0,0,0,0,0,0,0,0,0,0,0,0,0,0,0,0,0,0,0],[0,0,0,0,0,0,0,0,0,0,0,0,0,0,0,0,0,0,0,0,0,0,0,0,0,0,0,0,0,0,0,0,0,0,0,0,0,0,0,0,0,0,0,0,0,0,0,0,0,0],[0,0,0,0,0,0,0,0,0,0,0,0,0,0,0,0,0,0,0,0,0,0,0,0,0,0,0,0,0,0,0,0,0,0,0,0,0,0,0,0,0,0,0,0,0,0,0,0,0,0],[0,0,0,0,0,0,0,0,0,0,0,0,0,0,0,0,0,0,0,0,0,0,0,0,0,0,0,0,0,0,0,0,0,0,0,0,0,0,0,0,0,0,0,0,0,0,0,0,0,0],[0,0,0,0,0,0,0,0,0,0,0,0,0,0,0,0,0,0,0,0,0,0,0,0,0,0,0,0,0,0,0,0,0,0,0,0,0,0,0,0,0,0,0,0,0,0,0,0,0,0],[0,0,0,0,0,0,0,0,0,0,0,0,0,0,0,0,0,0,0,0,0,0,0,0,0,0,0,0,0,0,0,0,0,0,0,0,0,0,0,0,0,0,0,0,0,0,0,0,0,0]]},{"id":11,"type":"Background","name":"GroundGlow","level":"1","width":50,"height":45,"visible":1,"tilesetName":"media\/map\/final-dungeon-glow.png","repeat":false,"lighter":false,"distance":1,"yDistance":0,"tilesize":16,"moveSpeed":{"x":0,"y":0},"data":[[0,0,0,0,0,0,0,0,0,0,0,0,0,0,0,0,0,0,0,0,0,0,0,0,0,0,0,0,0,0,0,0,0,0,0,0,0,0,0,0,0,0,0,0,0,0,0,0,0,0],[0,0,0,0,0,0,0,0,0,0,0,0,0,0,0,0,0,0,0,0,0,0,0,0,0,0,0,0,0,0,0,0,0,0,0,0,0,0,0,0,0,0,0,0,0,0,0,0,0,0],[0,0,0,0,0,0,0,0,0,0,0,0,0,0,0,0,0,0,0,0,0,0,0,0,0,0,0,0,0,0,0,0,0,0,0,0,0,0,0,0,0,0,0,0,0,0,0,0,0,0],[0,0,0,0,0,0,0,0,0,0,0,0,0,0,0,0,0,0,0,0,0,0,0,0,0,0,0,0,0,0,0,0,0,0,0,0,0,0,0,0,0,0,0,0,0,0,0,0,0,0],[0,0,0,0,0,0,0,0,0,0,0,0,0,0,0,0,0,0,0,0,0,0,0,0,0,0,0,0,0,0,0,0,0,0,0,0,0,0,0,0,0,0,0,0,0,0,0,0,0,0],[0,0,0,0,0,0,0,0,0,0,0,0,0,0,0,0,0,0,0,0,0,0,0,0,0,0,0,0,0,0,0,0,0,0,0,0,0,0,0,0,0,0,0,0,0,0,0,0,0,0],[0,0,0,0,0,0,0,0,0,0,0,0,0,0,0,0,0,0,0,0,0,0,0,0,0,0,0,0,0,0,0,0,0,0,0,0,0,0,0,0,0,0,0,0,0,0,0,0,0,0],[0,0,0,0,0,0,0,0,0,0,0,0,0,0,0,0,0,0,0,0,0,0,0,0,0,0,0,0,0,0,0,0,0,0,0,0,131,0,0,0,0,0,0,0,0,0,0,0,0,0],[0,0,0,0,0,0,0,0,0,0,0,0,0,0,0,0,0,0,0,0,0,0,0,3,0,0,0,0,0,0,0,0,0,0,0,0,132,137,0,0,0,0,0,0,0,0,0,0,0,0],[0,0,0,0,0,0,0,0,0,0,0,0,0,0,0,0,0,0,0,0,0,0,0,3,0,0,0,0,0,0,0,0,0,0,0,0,0,0,0,0,0,0,0,0,0,0,0,0,0,0],[0,0,0,0,0,0,0,0,0,0,199,0,0,0,0,135,137,0,0,0,0,7,9,4,7,0,135,137,0,67,71,73,71,0,0,0,0,0,0,0,0,0,0,71,0,0,0,0,0,0],[0,0,0,0,0,0,0,0,0,0,0,0,0,0,0,0,0,0,0,0,4,0,0,35,0,0,0,0,0,68,0,0,0,0,0,0,0,0,0,0,0,0,0,0,0,0,0,0,0,0],[0,0,0,0,0,0,0,0,199,201,201,0,0,135,135,137,0,0,0,9,4,7,0,0,3,132,0,0,73,68,73,71,0,0,0,0,202,0,0,106,0,0,0,0,0,0,0,0,0,0],[0,0,0,0,0,0,0,22,22,22,22,22,0,0,0,0,0,0,0,0,0,0,0,0,4,163,22,22,22,99,22,22,22,0,0,202,236,0,0,107,106,0,0,0,0,0,0,0,0,0],[0,0,0,0,0,0,22,31,23,57,59,62,0,0,0,0,0,0,0,0,0,0,0,0,140,0,61,56,23,57,59,59,62,0,0,234,0,0,0,0,106,0,0,0,0,0,0,0,0,0],[0,0,0,0,0,0,22,57,59,62,0,0,0,0,0,0,171,168,168,0,0,0,0,0,172,107,0,28,57,62,40,40,0,0,0,234,0,0,0,0,106,0,0,0,0,0,0,0,0,0],[0,0,0,0,0,0,22,62,0,0,0,0,0,0,0,0,0,0,139,0,0,0,0,43,0,0,236,61,62,0,0,0,0,0,0,235,203,0,0,0,172,0,0,0,0,0,0,0,0,0],[0,0,0,0,0,0,22,0,0,0,0,0,0,0,0,0,140,172,171,0,0,0,0,0,43,236,0,0,0,0,0,0,0,0,0,0,0,11,140,0,0,55,0,0,0,0,0,0,0,0],[0,0,0,0,0,0,22,30,0,0,0,0,0,0,0,0,171,139,140,172,0,0,0,0,0,0,0,0,0,0,0,0,0,0,0,0,0,43,172,29,27,55,0,0,0,0,0,0,0,0],[0,0,0,0,0,0,22,25,30,0,0,0,0,0,0,0,0,170,170,0,0,0,0,0,0,0,0,0,0,0,0,0,0,0,0,0,0,29,27,24,60,0,0,0,0,0,0,0,0,0],[0,0,0,0,0,0,22,23,60,0,0,0,0,0,0,0,0,172,0,139,0,0,0,0,0,0,0,0,0,0,0,0,0,0,0,0,22,22,22,22,22,22,0,0,0,0,0,0,0,0],[0,0,0,0,0,0,22,57,62,0,0,0,0,0,0,0,0,0,0,0,0,0,0,0,0,0,0,22,22,0,0,0,0,0,0,0,0,0,0,0,0,0,0,0,0,0,0,0,0,0],[0,0,0,0,0,0,22,62,0,0,0,0,0,0,0,0,0,0,0,0,0,0,0,0,0,0,29,32,22,22,22,22,22,22,22,0,0,22,22,22,22,0,0,0,0,0,0,0,0,0],[0,0,0,0,0,0,0,0,0,0,0,0,0,0,0,0,0,170,170,0,0,0,0,0,0,0,61,59,56,23,23,23,57,59,62,0,0,61,59,56,25,32,0,0,0,0,0,0,0,0],[0,0,0,0,0,0,0,0,104,105,0,0,0,0,0,0,0,0,0,0,0,0,0,0,75,76,0,0,28,59,59,59,62,0,0,40,40,0,0,61,56,25,32,0,0,0,0,0,0,0],[0,0,0,0,0,0,22,30,0,0,0,0,0,0,0,0,0,0,0,0,0,0,0,0,74,74,0,29,60,0,0,0,0,0,0,0,0,0,0,0,28,23,25,22,0,0,0,0,0,0],[0,0,0,0,0,0,22,60,0,0,0,0,0,0,0,0,0,0,0,0,0,0,0,0,106,106,0,61,58,30,0,0,0,0,0,0,0,0,0,0,61,56,23,22,0,0,0,0,0,0],[0,0,0,0,0,0,22,60,0,0,0,0,0,0,0,0,0,0,0,0,0,0,0,204,108,107,139,0,61,62,0,0,0,0,0,0,0,0,0,0,0,61,56,22,0,0,0,0,0,0],[0,0,0,0,0,0,22,60,0,0,0,0,0,0,0,0,0,0,0,0,0,204,233,236,0,0,171,169,139,0,0,0,0,0,0,0,0,0,0,0,10,0,28,22,0,0,0,0,0,0],[0,0,0,0,0,0,22,60,0,0,0,0,0,0,0,0,0,0,0,0,0,235,233,203,0,0,140,169,172,0,0,0,0,0,0,0,0,0,0,0,42,0,28,22,0,0,0,0,0,0],[0,0,0,0,0,0,22,60,0,0,0,0,0,0,0,0,0,0,0,0,0,0,0,235,11,12,172,0,0,0,0,0,0,0,0,0,0,0,0,0,0,0,28,22,0,0,0,0,0,0],[0,0,0,0,0,0,22,60,0,0,0,0,0,0,0,0,0,0,0,0,55,0,0,0,42,42,0,29,27,30,0,0,0,0,0,0,0,0,0,0,0,0,28,22,0,0,0,0,0,0],[0,0,0,0,0,0,22,25,30,0,0,0,0,0,0,0,232,232,0,0,0,29,30,0,10,42,0,61,56,60,0,0,0,0,0,0,0,0,0,0,0,29,26,22,0,0,0,0,0,0],[0,0,0,0,0,0,22,23,60,0,0,0,0,0,0,0,0,0,0,0,0,28,62,0,44,43,0,0,28,60,55,0,0,0,0,0,0,0,0,0,0,28,60,0,0,0,0,0,0,0],[0,0,0,0,0,22,22,23,25,27,30,0,232,232,0,0,0,29,30,0,29,60,0,0,0,0,29,27,24,60,168,0,0,0,233,29,30,232,0,29,27,24,60,0,0,0,0,0,0,0],[0,0,0,0,0,0,22,63,23,23,25,27,27,27,30,0,0,28,25,27,24,25,27,30,0,0,61,56,57,62,0,0,0,0,29,24,25,27,27,24,23,57,62,0,0,0,0,0,0,0],[0,0,0,0,0,0,22,22,22,22,22,22,22,22,22,22,22,22,22,22,63,57,59,62,0,0,0,61,62,0,0,0,22,22,22,22,22,22,22,22,22,22,0,0,0,0,0,0,0,0],[0,0,0,0,0,0,0,22,22,22,0,0,0,0,0,0,0,0,0,0,22,60,0,0,0,0,0,0,0,0,0,0,0,0,0,0,0,0,0,0,0,0,22,22,22,0,0,0,0,0],[0,0,0,0,0,0,0,0,0,0,0,0,0,0,0,0,0,0,0,0,22,62,0,0,0,0,0,0,0,0,0,0,0,0,0,0,0,0,0,0,0,0,0,0,0,0,0,0,0,0],[0,0,0,0,0,0,0,0,0,0,0,0,0,0,0,0,0,0,0,0,0,0,0,0,0,0,0,0,0,0,0,0,0,0,0,0,0,0,0,0,0,0,0,0,0,0,0,0,0,0],[0,0,0,0,0,0,0,0,0,0,0,0,0,0,0,0,0,0,0,0,0,0,0,0,0,0,0,0,0,0,0,0,0,0,0,0,0,0,0,0,0,0,0,0,0,0,0,0,0,0],[0,0,0,0,0,0,0,0,0,0,0,0,0,0,0,0,0,0,0,0,0,0,0,0,0,0,0,0,0,0,0,0,0,0,0,0,0,0,0,0,0,0,0,0,0,0,0,0,0,0],[0,0,0,0,0,0,0,0,0,0,0,0,0,0,0,0,0,0,0,0,0,0,0,0,0,0,0,0,0,0,0,0,0,0,0,0,0,0,0,0,0,0,0,0,0,0,0,0,0,0],[0,0,0,0,0,0,0,0,0,0,0,0,0,0,0,0,0,0,0,0,0,0,0,0,0,0,0,0,0,0,0,0,0,0,0,0,0,0,0,0,0,0,0,0,0,0,0,0,0,0],[0,0,0,0,0,0,0,0,0,0,0,0,0,0,0,0,0,0,0,0,0,0,0,0,0,0,0,0,0,0,0,0,0,0,0,0,0,0,0,0,0,0,0,0,0,0,0,0,0,0]]},{"id":12,"type":"Navigation","name":"Navigation","level":"1","width":50,"height":45,"visible":1,"tilesetName":"media\/map\/pathmap-tiles.png","repeat":false,"lighter":false,"distance":1,"yDistance":0,"tilesize":16,"moveSpeed":{"x":0,"y":0},"data":[[0,0,0,0,0,0,0,0,0,0,0,0,0,0,0,0,0,0,0,0,0,0,0,0,0,0,0,0,0,0,0,0,0,0,0,0,0,0,0,0,0,0,0,0,0,0,0,0,0,0],[0,0,0,0,0,0,0,0,0,0,0,0,0,0,0,0,0,0,0,0,0,0,0,0,0,0,0,0,0,0,0,0,0,0,0,0,0,0,0,0,0,0,0,0,0,0,0,0,0,0],[0,0,0,0,0,0,0,0,0,0,0,0,0,0,0,0,0,0,0,0,0,0,0,0,0,0,0,0,0,0,0,0,0,0,0,0,0,0,0,0,0,0,0,0,0,0,0,0,0,0],[0,0,0,0,0,0,0,0,0,0,0,0,0,0,0,0,0,0,0,0,0,0,0,0,0,0,0,0,0,0,0,0,0,0,0,0,0,0,0,0,0,0,0,0,0,0,0,0,0,0],[0,0,0,0,0,0,0,0,0,0,0,0,0,0,0,0,0,0,0,0,0,0,0,0,0,0,0,0,0,0,0,0,0,0,0,0,0,0,0,0,0,0,0,0,0,0,0,0,0,0],[0,0,0,0,0,0,0,0,0,0,0,0,0,0,0,0,0,0,0,0,0,0,0,0,0,0,0,0,0,0,0,0,0,0,0,0,0,0,0,0,0,0,0,0,0,0,0,0,0,0],[0,0,0,0,0,0,0,0,0,0,0,0,0,0,0,0,0,0,0,0,0,0,0,0,0,0,0,0,0,0,0,0,0,0,0,0,0,0,0,0,0,0,0,0,0,0,0,0,0,0],[0,0,0,0,0,0,0,0,0,0,0,0,0,0,0,0,0,0,0,0,0,0,0,0,0,0,0,0,0,0,0,0,0,0,0,0,0,0,0,0,0,0,0,0,0,0,0,0,0,0],[0,0,0,0,0,0,0,0,0,0,0,0,0,0,0,0,0,0,0,0,0,0,0,0,0,0,0,0,0,0,0,0,0,0,0,0,0,0,0,0,0,0,0,0,0,0,0,0,0,0],[0,0,0,0,0,0,0,0,0,0,0,0,0,0,0,0,0,0,0,0,0,0,0,0,0,0,0,0,0,0,0,0,0,0,0,0,0,0,0,0,0,0,0,0,0,0,0,0,0,0],[0,0,0,0,0,0,0,0,0,0,0,0,0,0,0,0,0,0,0,0,0,0,0,0,0,0,0,0,0,0,0,0,0,0,0,0,0,0,0,0,0,0,0,0,0,0,0,0,0,0],[0,0,0,0,0,0,0,0,0,0,0,0,0,0,0,0,0,0,0,0,0,0,0,0,0,0,0,0,0,0,0,0,0,0,0,0,0,0,0,0,0,0,0,0,0,0,0,0,0,0],[0,0,0,0,0,0,0,0,0,0,0,0,0,0,0,0,0,0,0,0,0,0,0,0,0,0,0,0,0,0,0,0,0,0,0,0,1,1,1,1,0,0,0,0,0,0,0,0,0,0],[0,0,0,0,0,0,0,0,0,0,0,0,0,0,0,0,0,0,0,0,0,0,0,0,0,0,0,0,0,0,0,0,0,0,0,1,1,1,1,1,1,0,0,0,0,0,0,0,0,0],[0,0,0,0,0,0,0,0,3,3,3,1,1,1,1,1,1,1,1,1,1,1,1,3,3,3,3,2,2,2,2,2,2,2,2,1,1,1,1,1,1,2,0,0,0,0,0,0,0,0],[0,0,0,0,0,0,0,2,2,2,2,1,1,1,1,1,1,1,1,1,1,1,1,3,3,3,3,2,2,2,2,2,2,2,2,1,1,1,1,1,1,0,0,0,0,0,0,0,0,0],[0,0,0,0,0,0,0,2,2,2,2,1,1,1,1,1,1,1,1,1,1,1,1,3,3,3,3,2,2,2,2,2,2,2,2,1,1,1,1,1,1,0,0,0,0,0,0,0,0,0],[0,0,0,0,0,0,0,2,2,2,2,0,0,0,0,0,0,2,2,0,0,0,2,3,3,3,3,1,0,0,0,0,0,0,0,1,1,1,1,1,1,0,0,0,0,0,0,0,0,0],[0,0,0,0,0,0,0,1,1,1,0,0,0,0,0,0,0,2,2,0,0,0,0,3,3,3,3,0,0,0,0,0,0,0,0,1,1,1,1,1,1,0,0,0,0,0,0,0,0,0],[0,0,0,0,0,0,0,1,1,1,0,0,0,0,0,0,0,2,2,0,0,0,0,0,1,1,0,0,0,0,0,0,0,0,0,0,0,0,0,0,0,0,0,0,0,0,0,0,0,0],[0,0,0,0,0,0,0,1,1,1,0,0,0,0,0,0,0,2,2,0,0,0,0,0,1,1,0,0,0,0,0,0,0,0,0,0,0,0,0,0,0,0,0,0,0,0,0,0,0,0],[0,0,0,0,0,0,0,1,1,1,0,0,0,0,0,0,0,2,2,0,0,0,0,0,1,1,0,0,0,0,0,0,0,0,0,0,0,0,0,0,0,0,0,0,0,0,0,0,0,0],[0,0,0,0,0,0,0,1,1,1,0,0,0,0,0,0,0,2,2,0,0,0,0,0,1,1,0,0,0,0,0,0,0,0,0,0,0,0,0,0,0,0,0,0,0,0,0,0,0,0],[0,0,0,0,0,0,0,1,1,1,0,0,0,0,0,0,0,3,3,3,3,2,2,2,2,2,2,0,0,0,0,0,0,0,0,0,0,0,0,0,0,0,0,0,0,0,0,0,0,0],[0,0,0,0,0,0,0,1,1,1,2,2,2,2,2,2,2,3,3,3,3,1,1,1,1,1,1,1,1,3,3,2,2,2,2,2,2,2,2,3,3,0,0,0,0,0,0,0,0,0],[0,0,0,0,0,0,0,1,1,1,2,2,2,2,2,2,2,3,3,3,3,1,1,1,1,1,1,1,1,3,3,2,2,2,2,2,2,2,2,1,1,1,0,0,0,0,0,0,0,0],[0,0,0,0,0,0,0,1,1,1,0,0,0,0,0,0,0,0,0,0,0,1,1,1,1,1,1,1,1,3,3,0,0,0,0,0,0,0,3,1,1,1,0,0,0,0,0,0,0,0],[0,0,0,0,0,0,0,1,1,1,0,0,0,0,0,0,0,0,0,0,0,1,1,1,1,1,1,1,1,4,0,0,0,0,0,0,0,0,0,1,1,1,0,0,0,0,0,0,0,0],[0,0,0,0,0,0,0,1,1,1,0,0,0,0,0,0,0,0,0,0,0,1,1,1,1,1,1,1,1,4,0,0,0,0,0,0,0,0,0,1,1,1,0,0,0,0,0,0,0,0],[0,0,0,0,0,0,0,1,1,1,0,0,0,0,0,0,0,0,0,0,0,1,1,1,1,1,1,1,1,4,0,0,0,0,0,0,0,0,0,1,1,1,0,0,0,0,0,0,0,0],[0,0,0,0,0,0,0,1,1,1,0,0,0,0,0,0,0,0,0,0,0,1,1,1,1,1,1,1,1,4,0,0,0,0,0,0,0,0,0,1,1,1,0,0,0,0,0,0,0,0],[0,0,0,0,0,0,0,3,3,3,3,0,0,0,0,0,0,0,0,0,0,1,1,1,1,1,1,1,1,4,0,0,0,0,0,0,0,0,0,1,1,1,0,0,0,0,0,0,0,0],[0,0,0,0,0,0,0,1,2,2,2,2,2,2,2,2,2,2,2,2,2,1,1,1,1,1,1,1,1,2,2,0,0,0,0,0,0,0,2,2,2,2,0,0,0,0,0,0,0,0],[0,0,0,0,0,0,0,1,2,2,2,2,2,2,2,2,2,2,2,2,2,1,1,1,1,1,1,1,1,2,2,1,1,1,1,1,1,1,2,2,2,2,0,0,0,0,0,0,0,0],[0,0,0,0,0,0,0,1,2,2,2,2,2,2,2,2,2,2,2,2,2,1,1,1,1,1,1,1,1,2,2,1,1,1,1,1,1,1,2,2,2,2,0,0,0,0,0,0,0,0],[0,0,0,0,0,0,0,0,2,2,2,2,2,2,2,2,2,2,2,2,2,1,1,1,1,1,1,1,1,2,2,1,1,1,1,1,1,1,2,2,2,2,0,0,0,0,0,0,0,0],[0,0,0,0,0,0,0,0,0,0,0,0,0,0,0,0,0,0,0,0,0,1,1,1,1,1,1,1,1,0,0,0,0,0,0,0,0,0,0,0,0,0,0,0,0,0,0,0,0,0],[0,0,0,0,0,0,0,0,0,0,0,0,0,0,0,0,0,0,0,0,0,1,1,1,1,1,1,1,1,0,0,0,0,0,0,0,0,0,0,0,0,0,0,0,0,0,0,0,0,0],[0,0,0,0,0,0,0,0,0,0,0,0,0,0,0,0,0,0,0,0,0,1,1,1,1,1,1,1,1,0,0,0,0,0,0,0,0,0,0,0,0,0,0,0,0,0,0,0,0,0],[0,0,0,0,0,0,0,0,0,0,0,0,0,0,0,0,0,0,0,0,0,0,1,1,1,1,1,1,0,0,0,0,0,0,0,0,0,0,0,0,0,0,0,0,0,0,0,0,0,0],[0,0,0,0,0,0,0,0,0,0,0,0,0,0,0,0,0,0,0,0,0,0,0,0,0,0,0,0,0,0,0,0,0,0,0,0,0,0,0,0,0,0,0,0,0,0,0,0,0,0],[0,0,0,0,0,0,0,0,0,0,0,0,0,0,0,0,0,0,0,0,0,0,0,0,0,0,0,0,0,0,0,0,0,0,0,0,0,0,0,0,0,0,0,0,0,0,0,0,0,0],[0,0,0,0,0,0,0,0,0,0,0,0,0,0,0,0,0,0,0,0,0,0,0,0,0,0,0,0,0,0,0,0,0,0,0,0,0,0,0,0,0,0,0,0,0,0,0,0,0,0],[0,0,0,0,0,0,0,0,0,0,0,0,0,0,0,0,0,0,0,0,0,0,0,0,0,0,0,0,0,0,0,0,0,0,0,0,0,0,0,0,0,0,0,0,0,0,0,0,0,0],[0,0,0,0,0,0,0,0,0,0,0,0,0,0,0,0,0,0,0,0,0,0,0,0,0,0,0,0,0,0,0,0,0,0,0,0,0,0,0,0,0,0,0,0,0,0,0,0,0,0]]},{"id":5,"type":"Collision","name":"Collision","level":"1","width":50,"height":45,"visible":1,"tilesetName":"media\/map\/collisiontiles-16x16.png","repeat":false,"distance":1,"yDistance":0,"tilesize":16,"moveSpeed":{"x":0,"y":0},"data":[[2,2,2,2,2,2,2,2,2,2,2,2,2,2,2,2,2,2,2,2,2,2,2,2,2,2,2,2,2,2,2,2,2,2,2,2,2,2,2,2,2,2,2,2,2,2,2,2,2,2],[2,2,2,2,2,2,2,2,2,2,2,2,2,2,2,2,2,2,2,2,2,2,2,2,2,2,2,2,2,2,2,2,2,2,2,2,2,2,2,2,2,2,2,2,2,2,2,2,2,2],[2,2,2,2,2,2,2,2,2,2,2,2,2,2,2,2,2,2,2,2,2,2,2,2,2,2,2,2,2,2,2,2,2,2,2,2,2,2,2,2,2,2,2,2,2,2,2,2,2,2],[2,2,2,2,2,2,2,2,2,2,2,2,2,2,2,2,2,2,2,2,2,2,2,2,2,2,2,2,2,2,2,2,2,2,2,2,2,2,2,2,2,2,2,2,2,2,2,2,2,2],[2,2,2,2,2,2,2,2,2,2,2,2,2,2,2,2,2,2,2,2,2,2,2,2,2,2,2,2,2,2,2,2,2,2,2,2,2,2,2,2,2,2,2,2,2,2,2,2,2,2],[2,2,2,2,2,2,2,2,2,2,2,2,2,2,2,2,2,2,2,2,2,2,2,2,2,2,2,2,2,2,2,2,2,2,2,2,2,2,2,2,2,2,2,2,2,2,2,2,2,2],[2,2,2,2,2,2,2,2,2,2,2,2,2,2,2,2,2,2,2,2,2,2,2,2,2,2,2,2,2,2,2,2,2,2,2,2,2,2,2,2,2,2,2,2,2,2,2,2,2,2],[2,2,2,2,2,2,2,2,2,2,2,2,2,2,2,2,2,2,2,2,2,2,2,2,2,2,2,2,2,2,2,2,2,2,2,2,2,2,2,2,2,2,2,2,2,2,2,2,2,2],[2,2,2,2,2,2,2,2,2,2,2,2,2,2,2,2,2,2,2,2,2,2,2,2,2,2,2,2,2,2,2,2,2,2,2,2,2,2,2,2,2,2,2,2,2,2,2,2,2,2],[2,2,2,2,2,2,2,2,2,2,2,2,2,2,2,2,2,2,2,2,2,2,2,2,2,2,2,2,2,2,2,2,2,2,2,2,2,2,2,2,2,2,2,2,2,2,2,2,2,2],[2,2,2,2,2,2,2,2,2,2,2,2,2,2,2,2,2,2,2,2,2,2,2,2,2,2,2,2,2,2,2,2,2,2,2,2,2,2,2,2,2,2,2,2,2,2,2,2,2,2],[2,2,2,2,2,2,2,2,2,2,2,2,2,2,2,2,2,2,2,2,2,2,2,2,2,2,2,2,2,2,2,2,2,2,2,2,2,2,2,2,2,2,2,2,2,2,2,2,2,2],[2,2,2,2,2,2,2,2,2,2,2,2,2,2,2,2,2,2,2,2,2,2,2,2,2,2,2,2,2,2,2,2,2,2,2,9,0,0,0,0,10,2,2,2,2,2,2,2,2,2],[2,2,2,2,2,2,2,2,2,2,2,2,2,2,2,2,2,2,2,2,2,2,2,2,2,2,2,2,2,2,2,2,2,2,2,0,0,0,0,0,0,2,2,2,2,2,2,2,2,2],[2,2,2,2,2,2,2,9,0,0,0,0,0,0,0,0,0,0,0,0,0,0,0,0,0,0,0,0,0,0,0,0,0,0,0,0,0,0,0,0,0,0,1,1,26,2,2,2,2,2],[2,2,2,2,2,2,2,0,0,0,0,0,0,0,0,0,0,0,0,0,0,0,0,0,0,0,0,0,0,0,0,0,0,0,0,0,0,0,0,0,0,0,1,1,1,2,2,2,2,2],[2,2,2,2,2,2,2,0,0,0,0,0,0,0,0,0,0,0,0,0,0,0,0,0,0,0,0,0,0,0,0,0,0,0,0,0,0,0,0,0,0,0,1,1,1,2,2,2,2,2],[2,2,2,2,2,2,2,0,0,0,0,0,0,0,0,0,0,0,0,0,0,0,0,0,0,0,0,0,0,0,0,0,0,0,0,0,0,0,0,0,0,0,1,1,1,2,2,2,2,2],[2,2,2,2,2,2,2,0,0,0,0,7,1,1,1,1,0,0,0,0,1,4,0,0,0,0,0,0,7,1,1,1,1,1,0,0,0,0,0,0,0,0,1,1,1,2,2,2,2,2],[2,2,2,2,2,2,2,0,0,0,0,1,1,1,1,1,0,0,0,0,1,1,4,0,0,0,0,7,1,1,1,1,1,1,4,0,0,0,0,0,0,7,1,1,1,2,2,2,2,2],[2,2,2,2,2,2,2,0,0,0,0,1,1,1,1,1,0,0,0,0,1,1,1,0,0,0,0,1,1,1,1,1,1,1,1,1,1,1,1,1,1,1,1,1,1,2,2,2,2,2],[2,2,2,2,2,2,2,0,0,0,0,1,1,1,1,1,0,0,0,0,1,1,1,0,0,0,0,1,1,1,1,1,1,1,1,1,1,1,1,1,1,1,1,1,1,2,2,2,2,2],[2,2,2,2,2,2,2,0,0,0,0,1,1,1,1,1,0,0,0,0,0,0,0,0,0,0,0,6,1,1,1,1,1,1,1,1,1,1,1,1,1,1,1,1,1,2,2,2,2,2],[2,2,2,2,2,2,2,0,0,0,0,0,0,0,0,0,0,0,0,0,0,0,0,0,0,0,0,0,0,0,0,0,0,0,0,0,0,0,0,0,0,6,1,1,1,2,2,2,2,2],[2,2,2,2,2,2,2,0,0,0,0,0,0,0,0,0,0,0,0,0,0,0,0,0,0,0,0,0,0,0,0,0,0,0,0,0,0,0,0,0,0,0,6,1,1,2,2,2,2,2],[2,2,2,2,2,2,2,0,0,0,0,0,0,0,0,0,0,0,0,0,0,0,0,0,0,0,0,0,0,0,0,0,0,0,0,0,0,0,0,0,0,0,0,1,1,2,2,2,2,2],[2,2,2,2,2,2,2,0,0,0,0,0,0,0,0,0,0,0,0,0,0,0,0,0,0,0,0,0,0,0,7,1,1,1,1,1,1,1,4,0,0,0,0,1,1,2,2,2,2,2],[2,2,2,2,2,2,2,0,0,0,0,1,1,1,1,1,1,1,1,1,0,0,0,0,0,0,0,0,0,0,1,1,1,1,1,1,1,1,1,0,0,0,0,1,1,2,2,2,2,2],[2,2,2,2,2,2,2,0,0,0,0,1,1,1,1,1,1,1,1,1,0,0,0,0,0,0,0,0,0,0,1,1,1,5,0,6,1,1,1,0,0,0,0,1,1,2,2,2,2,2],[2,2,2,2,2,2,2,0,0,0,0,1,1,1,1,1,1,1,1,1,0,0,0,0,0,0,0,0,0,0,1,1,1,0,0,0,1,1,1,0,0,0,0,1,1,2,2,2,2,2],[2,2,2,2,2,2,2,0,0,0,0,6,1,1,1,1,1,1,1,1,0,0,0,0,0,0,0,0,0,0,1,1,1,4,0,7,1,1,1,0,0,0,0,1,1,2,2,2,2,2],[2,2,2,2,2,2,2,0,0,0,0,0,0,0,0,0,0,0,0,0,0,0,0,0,0,0,0,0,0,0,1,1,1,1,1,1,1,1,1,0,0,0,0,1,1,2,2,2,2,2],[2,2,2,2,2,2,2,0,0,0,0,0,0,0,0,0,0,0,0,0,0,0,0,0,0,0,0,0,0,0,6,1,1,1,1,1,1,1,5,0,0,0,0,1,1,2,2,2,2,2],[2,2,2,2,2,2,2,0,0,0,0,0,0,0,0,0,0,0,0,0,0,0,0,0,0,0,0,0,0,0,0,0,0,0,0,0,0,0,0,0,0,0,0,1,1,2,2,2,2,2],[2,2,2,2,2,2,2,0,0,0,0,0,0,0,0,0,0,0,0,0,0,0,0,0,0,0,0,0,0,0,0,0,0,0,0,0,0,0,0,0,0,0,0,1,1,2,2,2,2,2],[2,2,2,2,2,2,2,8,0,0,0,0,0,0,0,0,0,0,0,0,0,0,0,0,0,0,0,0,0,0,0,0,0,0,0,0,0,0,0,0,0,0,0,1,27,2,2,2,2,2],[2,2,2,2,2,2,2,2,2,2,2,2,2,2,2,2,2,2,2,2,8,0,0,0,0,0,0,0,0,11,2,2,2,2,2,2,2,2,2,2,2,2,2,2,2,2,2,2,2,2],[2,2,2,2,2,2,2,2,2,2,2,2,2,2,2,2,2,2,2,2,2,0,0,0,0,0,0,0,0,2,2,2,2,2,2,2,2,2,2,2,2,2,2,2,2,2,2,2,2,2],[2,2,2,2,2,2,2,2,2,2,2,2,2,2,2,2,2,2,2,2,2,0,0,0,0,0,0,0,0,2,2,2,2,2,2,2,2,2,2,2,2,2,2,2,2,2,2,2,2,2],[2,2,2,2,2,2,2,2,2,2,2,2,2,2,2,2,2,2,2,2,2,8,0,0,0,0,0,0,11,2,2,2,2,2,2,2,2,2,2,2,2,2,2,2,2,2,2,2,2,2],[2,2,2,2,2,2,2,2,2,2,2,2,2,2,2,2,2,2,2,2,2,2,2,2,2,2,2,2,2,2,2,2,2,2,2,2,2,2,2,2,2,2,2,2,2,2,2,2,2,2],[2,2,2,2,2,2,2,2,2,2,2,2,2,2,2,2,2,2,2,2,2,2,2,2,2,2,2,2,2,2,2,2,2,2,2,2,2,2,2,2,2,2,2,2,2,2,2,2,2,2],[2,2,2,2,2,2,2,2,2,2,2,2,2,2,2,2,2,2,2,2,2,2,2,2,2,2,2,2,2,2,2,2,2,2,2,2,2,2,2,2,2,2,2,2,2,2,2,2,2,2],[2,2,2,2,2,2,2,2,2,2,2,2,2,2,2,2,2,2,2,2,2,2,2,2,2,2,2,2,2,2,2,2,2,2,2,2,2,2,2,2,2,2,2,2,2,2,2,2,2,2],[2,2,2,2,2,2,2,2,2,2,2,2,2,2,2,2,2,2,2,2,2,2,2,2,2,2,2,2,2,2,2,2,2,2,2,2,2,2,2,2,2,2,2,2,2,2,2,2,2,2]]},{"id":6,"type":"Background","name":"Upper","level":"2","width":50,"height":45,"visible":1,"tilesetName":"media\/map\/final-dungeon-inner.png","repeat":false,"distance":1,"yDistance":0,"tilesize":16,"moveSpeed":{"x":0,"y":0},"data":[[0,0,0,0,0,0,0,0,0,0,0,0,0,0,0,0,0,0,0,0,0,0,0,0,0,0,0,0,0,0,0,0,0,0,0,0,0,0,0,0,0,0,0,0,0,0,0,0,0,0],[0,0,0,0,0,0,0,0,0,0,0,0,0,0,0,0,0,0,0,0,0,0,0,0,0,0,0,0,0,0,0,0,0,0,0,0,0,0,0,0,0,0,0,0,0,0,0,0,0,0],[0,0,0,0,0,0,0,0,0,0,0,0,0,0,0,0,0,0,0,0,0,0,0,0,0,0,0,0,0,0,0,0,0,0,0,0,0,0,0,0,0,0,0,0,0,0,0,0,0,0],[0,0,0,0,0,0,0,0,0,0,0,0,0,0,0,0,0,0,0,0,0,0,0,0,0,0,0,0,0,0,0,0,0,0,0,0,0,0,0,0,0,0,0,0,0,0,0,0,0,0],[0,0,0,0,0,0,0,0,0,0,0,0,0,0,0,0,0,0,0,0,0,0,0,0,0,0,0,0,0,0,0,0,0,0,0,0,0,0,0,0,0,0,0,0,0,0,0,0,0,0],[0,0,0,0,0,0,0,0,0,0,0,0,0,0,0,0,0,0,0,0,0,0,0,0,0,0,0,0,0,0,0,0,0,0,0,0,0,0,0,0,0,0,0,0,0,0,0,0,0,0],[0,0,0,0,0,0,0,0,0,0,0,0,0,0,0,0,0,0,0,0,0,0,0,0,0,0,0,0,0,0,0,0,0,0,0,0,0,0,0,0,0,0,0,0,0,0,0,0,0,0],[0,0,0,0,0,0,0,0,0,0,0,0,0,0,0,0,0,0,0,0,0,0,0,0,0,0,0,0,0,0,0,0,0,0,0,0,0,0,0,0,0,0,0,0,0,0,0,0,0,0],[0,0,0,0,0,0,0,0,0,0,0,0,0,0,0,0,0,0,0,0,0,0,0,0,0,0,0,0,0,0,0,0,0,0,0,0,0,0,0,0,0,0,0,0,0,0,0,0,0,0],[0,0,0,0,0,0,0,0,0,0,0,0,0,0,0,0,0,0,0,0,0,0,0,0,0,0,0,0,0,0,0,0,0,0,0,199,199,199,199,199,199,0,0,0,0,0,0,0,0,0],[0,0,0,0,0,0,0,0,0,0,0,0,0,0,0,0,0,0,0,0,0,0,0,0,0,0,0,0,0,0,0,0,0,0,199,199,0,0,0,0,199,199,0,0,0,0,0,0,0,0],[0,0,0,0,0,0,0,199,199,199,199,199,199,199,199,199,199,199,199,199,199,199,199,199,199,199,199,199,199,199,199,199,199,199,199,0,0,0,0,0,0,199,199,199,199,0,0,0,0,0],[0,0,0,0,0,0,199,199,0,0,0,0,0,0,0,0,0,0,0,0,0,0,0,0,0,0,0,0,0,0,0,0,0,0,0,0,0,0,0,0,0,0,0,0,199,199,0,0,0,0],[0,0,0,0,0,0,0,0,0,0,0,0,0,0,0,0,0,0,0,0,0,0,0,0,0,0,0,0,0,0,0,0,0,0,0,0,0,0,0,0,0,0,0,0,0,0,0,0,0,0],[0,0,0,0,0,0,0,0,0,0,0,0,0,0,0,0,0,0,0,0,0,0,0,0,0,0,0,0,0,0,0,0,0,0,0,0,0,0,0,0,0,0,0,0,0,0,0,0,0,0],[0,0,0,0,0,0,0,0,0,0,0,0,0,0,0,0,0,0,0,0,0,0,0,0,0,0,0,0,0,0,0,0,0,0,0,0,0,0,0,0,0,0,0,0,0,0,0,0,0,0],[0,0,0,0,0,0,0,0,0,0,0,0,0,0,0,0,0,0,0,0,0,0,0,0,0,0,0,0,0,0,0,0,0,0,0,0,0,0,0,0,0,0,0,0,0,0,0,0,0,0],[0,0,0,0,0,0,0,0,0,0,0,0,0,0,0,0,0,0,0,0,0,0,0,0,0,0,0,0,0,0,0,0,0,0,0,0,0,0,0,0,0,0,0,0,0,0,0,0,0,0],[0,0,0,0,0,0,0,0,0,0,0,0,0,0,0,0,0,0,0,0,0,0,0,0,0,0,0,0,0,0,0,0,0,0,0,0,0,0,0,0,0,0,0,0,0,0,0,0,0,0],[0,0,0,0,0,0,0,0,0,0,0,0,0,0,0,0,0,0,0,0,0,0,0,0,0,0,0,0,0,0,0,0,0,0,0,0,0,0,0,0,0,0,0,0,0,0,0,0,0,0],[0,0,0,0,0,0,0,0,0,0,0,0,0,0,0,0,0,0,0,0,0,0,0,0,0,0,0,0,0,0,0,0,0,0,0,0,0,0,0,0,0,0,0,0,0,0,0,0,0,0],[0,0,0,0,0,0,0,0,0,0,0,0,0,0,0,0,0,0,0,0,0,0,0,0,0,0,0,0,0,0,0,0,0,0,0,0,0,0,0,0,0,0,0,0,0,0,0,0,0,0],[0,0,0,0,0,0,0,0,0,0,0,0,0,0,0,0,0,0,0,0,0,0,0,0,0,0,0,0,0,0,0,0,0,0,0,0,0,0,0,0,0,0,0,0,0,0,0,0,0,0],[0,0,0,0,0,0,0,0,0,0,0,0,0,0,0,0,0,0,0,0,0,0,0,0,0,0,0,0,0,0,0,0,0,0,0,0,0,0,0,0,0,0,0,0,0,0,0,0,0,0],[0,0,0,0,0,0,0,0,0,0,0,0,0,0,0,0,0,0,0,0,0,0,0,0,0,0,0,0,0,0,0,0,0,0,0,0,0,0,0,0,0,0,0,0,0,0,0,0,0,0],[0,0,0,0,0,0,0,0,0,0,0,0,0,0,0,0,0,0,0,0,0,0,0,0,0,0,0,0,0,0,0,0,0,0,0,0,0,0,0,0,0,0,0,0,0,0,0,0,0,0],[0,0,0,0,0,0,0,0,0,0,0,0,0,0,0,0,0,0,0,0,0,0,0,0,0,0,0,0,0,0,0,0,0,0,0,0,0,0,0,0,0,0,0,0,0,0,0,0,0,0],[0,0,0,0,0,0,0,0,0,0,0,0,0,0,0,0,0,0,0,0,0,0,0,0,0,0,0,0,0,0,0,0,0,0,0,0,0,0,0,0,0,0,0,0,0,0,0,0,0,0],[0,0,0,0,0,0,0,0,0,0,0,0,0,0,0,0,0,0,0,0,0,0,0,0,0,0,0,0,0,0,0,0,0,0,0,0,0,0,0,0,0,0,0,0,0,0,0,0,0,0],[0,0,0,0,0,0,0,0,0,0,0,0,0,0,0,0,0,0,0,0,0,0,0,0,0,0,0,0,0,0,0,0,0,0,0,0,0,0,0,0,0,0,0,0,0,0,0,0,0,0],[0,0,0,0,0,0,0,0,0,0,0,0,0,0,0,0,0,0,0,0,0,0,0,0,0,0,0,0,0,0,0,0,0,0,0,0,0,0,0,0,0,0,0,0,0,0,0,0,0,0],[0,0,0,0,0,0,0,0,0,0,0,0,0,0,0,0,0,0,0,0,0,0,0,0,0,0,0,0,0,0,0,0,0,0,0,0,0,0,0,0,0,0,0,0,0,0,0,0,0,0],[0,0,0,0,0,0,0,0,0,0,0,0,0,0,0,0,0,0,0,0,0,0,0,0,0,0,0,0,0,0,0,0,0,0,0,0,0,0,0,0,0,0,0,0,0,0,0,0,0,0],[0,0,0,0,0,0,0,0,0,0,0,0,0,0,0,0,0,0,0,0,0,0,0,0,0,0,0,0,0,0,0,0,0,0,0,0,0,0,0,0,0,0,0,0,0,0,0,0,0,0],[0,0,0,0,0,0,0,0,0,0,0,0,0,0,0,0,0,0,0,0,0,0,0,0,0,0,0,0,0,0,0,0,0,0,0,0,0,0,0,0,0,0,0,0,0,0,0,0,0,0],[0,0,0,0,0,0,0,0,0,0,0,0,0,0,0,0,0,0,0,0,0,0,0,0,0,0,0,0,0,0,0,0,0,0,0,0,0,0,0,0,0,0,0,0,0,0,0,0,0,0],[0,0,0,0,0,0,0,0,0,0,0,0,0,0,0,0,0,0,0,0,0,0,0,0,0,0,0,0,0,0,0,0,0,0,0,0,0,0,0,0,0,0,0,0,0,0,0,0,0,0],[0,0,0,0,0,0,0,0,0,0,0,0,0,0,0,0,0,0,0,0,0,0,0,0,0,0,0,0,0,0,0,0,0,0,0,0,0,0,0,0,0,0,0,0,0,0,0,0,0,0],[0,0,0,0,0,0,0,0,0,0,0,0,0,0,0,0,0,0,0,0,0,0,0,0,0,0,0,0,0,0,0,0,0,0,0,0,0,0,0,0,0,0,0,0,0,0,0,0,0,0],[0,0,0,0,0,0,0,0,0,0,0,0,0,0,0,0,0,0,0,0,0,0,0,0,0,0,0,0,0,0,0,0,0,0,0,0,0,0,0,0,0,0,0,0,0,0,0,0,0,0],[0,0,0,0,0,0,0,0,0,0,0,0,0,0,0,0,0,0,0,0,0,0,0,0,0,0,0,0,0,0,0,0,0,0,0,0,0,0,0,0,0,0,0,0,0,0,0,0,0,0],[0,0,0,0,0,0,0,0,0,0,0,0,0,0,0,0,0,0,0,0,0,0,0,0,0,0,0,0,0,0,0,0,0,0,0,0,0,0,0,0,0,0,0,0,0,0,0,0,0,0],[0,0,0,0,0,0,0,0,0,0,0,0,0,0,0,0,0,0,0,0,0,0,0,0,0,0,0,0,0,0,0,0,0,0,0,0,0,0,0,0,0,0,0,0,0,0,0,0,0,0],[0,0,0,0,0,0,0,0,0,0,0,0,0,0,0,0,0,0,0,0,0,0,0,0,0,0,0,0,0,0,0,0,0,0,0,0,0,0,0,0,0,0,0,0,0,0,0,0,0,0],[0,0,0,0,0,0,0,0,0,0,0,0,0,0,0,0,0,0,0,0,0,0,0,0,0,0,0,0,0,0,0,0,0,0,0,0,0,0,0,0,0,0,0,0,0,0,0,0,0,0]]},{"id":7,"type":"Background","name":"UpperDetails","level":"2","width":50,"height":45,"visible":1,"tilesetName":"media\/map\/final-dungeon-inner.png","repeat":false,"distance":1,"yDistance":0,"tilesize":16,"moveSpeed":{"x":0,"y":0},"data":[[0,0,0,0,0,0,0,0,0,0,0,0,0,0,0,0,0,0,0,0,0,0,0,0,0,0,0,0,0,0,0,0,0,0,0,0,0,0,0,0,0,0,0,0,0,0,0,0,0,0],[0,0,0,0,0,0,0,0,0,0,0,0,0,0,0,0,0,0,0,0,0,0,0,0,0,0,0,0,0,0,0,0,0,0,0,0,0,0,0,0,0,0,0,0,0,0,0,0,0,0],[0,0,0,0,0,0,0,0,0,0,0,0,0,0,0,0,0,0,0,0,0,0,0,0,0,0,0,0,0,0,0,0,0,0,0,0,0,0,0,0,0,0,0,0,0,0,0,0,0,0],[0,0,0,0,0,0,0,0,0,0,0,0,0,0,0,0,0,0,0,0,0,0,0,0,0,0,0,0,0,0,0,0,0,0,0,0,0,0,0,0,0,0,0,0,0,0,0,0,0,0],[0,0,0,0,0,0,0,0,0,0,0,0,0,0,0,0,0,0,0,0,0,0,0,0,0,0,0,0,0,0,0,0,0,0,0,0,0,0,0,0,0,0,0,0,0,0,0,0,0,0],[0,0,0,0,0,0,0,0,0,0,0,0,0,0,0,0,0,0,0,0,0,0,0,0,0,0,0,0,0,0,0,0,0,0,0,0,0,0,0,0,0,0,0,0,0,0,0,0,0,0],[0,0,0,0,0,0,0,0,0,0,0,0,0,0,0,0,0,0,0,0,0,0,0,0,0,0,0,0,0,0,0,0,0,0,0,0,0,0,0,0,0,0,0,0,0,0,0,0,0,0],[0,0,0,0,0,0,0,0,0,0,0,0,0,0,0,0,0,0,0,0,0,0,0,0,0,0,0,0,0,0,0,0,0,0,0,0,0,0,0,0,0,0,0,0,0,0,0,0,0,0],[0,0,0,0,0,0,0,0,0,0,0,0,0,0,0,0,0,0,0,0,0,0,0,0,0,0,0,0,0,0,0,0,0,0,0,0,0,0,0,0,0,0,0,0,0,0,0,0,0,0],[0,0,0,0,0,0,0,0,0,0,0,0,0,0,0,0,0,0,0,0,0,0,0,0,0,0,0,0,0,0,0,0,0,0,0,0,0,0,0,0,0,0,0,0,0,0,0,0,0,0],[0,0,0,0,0,0,0,0,0,0,0,0,0,0,0,0,0,0,0,0,0,0,0,0,0,0,0,0,0,0,0,0,0,0,0,0,0,0,0,0,0,0,0,0,0,0,0,0,0,0],[0,0,0,0,0,0,0,0,0,0,0,0,0,0,0,0,0,0,0,0,0,0,0,0,0,0,0,0,0,0,0,0,0,0,0,0,0,0,0,0,0,0,0,0,0,0,0,0,0,0],[0,0,0,0,0,0,0,0,0,0,0,0,0,0,0,0,0,0,0,0,0,0,0,0,0,0,0,0,0,0,0,0,0,0,0,0,0,0,0,0,0,0,0,0,0,0,0,0,0,0],[0,0,0,0,0,0,0,0,0,0,0,0,0,0,0,0,0,0,0,0,0,0,0,0,0,0,0,0,0,0,0,0,0,0,0,0,0,0,0,0,0,0,0,0,0,0,0,0,0,0],[0,0,0,0,0,0,0,0,0,0,0,0,0,0,0,0,0,0,0,0,0,0,0,0,0,0,0,0,0,0,0,0,0,0,0,0,0,0,0,0,0,0,0,0,0,0,0,0,0,0],[0,0,0,0,0,0,0,0,0,0,0,0,0,0,0,0,0,0,0,0,0,0,0,0,0,0,0,0,0,0,0,0,0,0,0,0,0,0,0,0,0,0,0,0,0,0,0,0,0,0],[0,0,0,0,0,0,0,0,0,0,0,0,0,0,0,0,0,0,0,0,0,0,0,0,0,0,0,0,0,0,0,0,0,0,0,0,0,0,0,0,0,0,0,0,0,0,0,0,0,0],[0,0,0,0,0,0,0,0,0,0,0,0,0,0,0,0,0,0,0,0,0,0,0,0,0,0,0,0,0,0,0,0,0,0,0,0,0,0,0,0,0,0,0,0,0,0,0,0,0,0],[0,0,0,0,0,0,0,0,0,0,0,0,0,0,0,0,0,0,0,0,0,0,0,0,0,0,0,0,0,0,0,0,0,0,0,0,0,0,0,0,0,0,0,0,0,0,0,0,0,0],[0,0,0,0,0,0,0,0,0,0,0,0,0,0,0,0,0,0,0,0,0,0,0,0,0,0,0,0,0,0,0,0,0,0,0,0,0,0,0,0,0,0,0,0,0,0,0,0,0,0],[0,0,0,0,0,0,0,0,0,0,0,0,0,0,0,0,0,0,0,0,0,0,0,0,0,0,0,0,0,0,0,0,0,0,0,0,0,0,0,0,0,0,0,0,0,0,0,0,0,0],[0,0,0,0,0,0,0,0,0,0,0,0,0,0,0,0,0,0,0,0,0,0,0,0,0,0,0,0,0,0,0,0,0,0,0,0,0,0,0,0,0,0,0,0,0,0,0,0,0,0],[0,0,0,0,0,0,0,0,0,0,0,0,0,0,0,0,0,0,0,0,0,0,0,0,0,0,0,0,0,0,0,0,0,0,0,0,0,0,0,0,0,0,0,0,0,0,0,0,0,0],[0,0,0,0,0,0,0,0,0,0,0,0,0,0,0,0,0,0,0,0,0,0,0,0,0,0,0,0,0,0,0,0,0,0,0,0,0,0,0,0,0,0,0,0,0,0,0,0,0,0],[0,0,0,0,0,0,0,0,0,0,0,0,0,0,0,0,0,0,0,0,0,0,0,0,0,0,0,0,0,0,0,0,0,0,0,0,0,0,0,0,0,0,0,0,0,0,0,0,0,0],[0,0,0,0,0,0,0,0,0,0,0,0,0,0,0,0,0,0,0,0,0,0,0,0,0,0,0,0,0,0,0,0,0,0,0,0,0,0,0,0,0,0,0,0,0,0,0,0,0,0],[0,0,0,0,0,0,0,0,0,0,0,0,0,0,0,0,0,0,0,0,0,0,0,0,0,0,0,0,0,0,0,0,0,0,0,0,0,0,0,0,0,0,0,0,0,0,0,0,0,0],[0,0,0,0,0,0,0,0,0,0,0,0,0,0,0,0,0,0,0,0,0,0,0,0,0,0,0,0,0,0,0,0,0,0,0,0,0,0,0,0,0,0,0,0,0,0,0,0,0,0],[0,0,0,0,0,0,0,0,0,0,0,0,0,0,0,0,0,0,0,0,0,0,0,0,0,0,0,0,0,0,0,0,0,0,0,0,0,0,0,0,0,0,0,0,0,0,0,0,0,0],[0,0,0,0,0,0,0,0,0,0,0,0,0,0,0,0,0,0,0,0,0,0,0,0,0,0,0,0,0,0,0,0,0,0,0,0,0,0,0,0,0,0,0,0,0,0,0,0,0,0],[0,0,0,0,0,0,0,0,0,0,0,0,0,0,0,0,0,0,0,0,0,0,0,0,0,0,0,0,0,0,0,0,0,0,0,0,0,0,0,0,0,0,0,0,0,0,0,0,0,0],[0,0,0,0,0,0,0,0,0,0,0,0,0,0,0,0,0,0,0,0,0,0,0,0,0,0,0,0,0,0,0,0,0,0,0,0,0,0,0,0,0,0,0,0,0,0,0,0,0,0],[0,0,0,0,0,0,0,0,0,0,0,0,0,0,0,0,0,0,0,0,0,0,0,0,0,0,0,0,0,0,0,0,0,0,0,0,0,0,0,0,0,0,0,0,0,0,0,0,0,0],[0,0,0,0,0,0,0,0,0,0,0,0,0,0,0,0,0,0,0,0,0,0,0,0,0,0,0,0,0,0,0,0,0,0,0,0,0,0,0,0,0,0,0,0,0,0,0,0,0,0],[0,0,0,0,0,0,0,0,0,0,0,0,0,0,0,0,0,0,0,0,0,0,0,0,0,0,0,0,0,0,0,0,0,0,0,0,0,0,0,0,0,0,0,0,0,0,0,0,0,0],[0,0,0,0,0,0,0,0,0,0,0,0,0,0,0,0,0,0,0,0,0,0,0,0,0,0,0,0,0,0,0,0,0,0,0,0,0,0,0,0,0,0,0,0,0,0,0,0,0,0],[0,0,0,0,0,0,0,0,0,0,0,0,0,0,0,0,0,0,0,0,0,0,0,0,0,0,0,0,0,0,0,0,0,0,0,0,0,0,0,0,0,0,0,0,0,0,0,0,0,0],[0,0,0,0,0,0,0,0,0,0,0,0,0,0,0,0,0,0,0,0,0,0,0,0,0,0,0,0,0,0,0,0,0,0,0,0,0,0,0,0,0,0,0,0,0,0,0,0,0,0],[0,0,0,0,0,0,0,0,0,0,0,0,0,0,0,0,0,0,0,0,0,0,0,0,0,0,0,0,0,0,0,0,0,0,0,0,0,0,0,0,0,0,0,0,0,0,0,0,0,0],[0,0,0,0,0,0,0,0,0,0,0,0,0,0,0,0,0,0,0,0,0,0,0,0,0,0,0,0,0,0,0,0,0,0,0,0,0,0,0,0,0,0,0,0,0,0,0,0,0,0],[0,0,0,0,0,0,0,0,0,0,0,0,0,0,0,0,0,0,0,0,0,0,0,0,0,0,0,0,0,0,0,0,0,0,0,0,0,0,0,0,0,0,0,0,0,0,0,0,0,0],[0,0,0,0,0,0,0,0,0,0,0,0,0,0,0,0,0,0,0,0,0,0,0,0,0,0,0,0,0,0,0,0,0,0,0,0,0,0,0,0,0,0,0,0,0,0,0,0,0,0],[0,0,0,0,0,0,0,0,0,0,0,0,0,0,0,0,0,0,0,0,0,0,0,0,0,0,0,0,0,0,0,0,0,0,0,0,0,0,0,0,0,0,0,0,0,0,0,0,0,0],[0,0,0,0,0,0,0,0,0,0,0,0,0,0,0,0,0,0,0,0,0,0,0,0,0,0,0,0,0,0,0,0,0,0,0,0,0,0,0,0,0,0,0,0,0,0,0,0,0,0],[0,0,0,0,0,0,0,0,0,0,0,0,0,0,0,0,0,0,0,0,0,0,0,0,0,0,0,0,0,0,0,0,0,0,0,0,0,0,0,0,0,0,0,0,0,0,0,0,0,0]]},{"id":8,"type":"Collision","name":"Collision","level":"2","width":50,"height":45,"visible":1,"tilesetName":"media\/map\/collisiontiles-16x16.png","repeat":false,"distance":1,"yDistance":0,"tilesize":16,"moveSpeed":{"x":0,"y":0},"data":[[2,2,2,2,2,2,2,2,2,2,2,2,2,2,2,2,2,2,2,2,2,2,2,2,2,2,2,2,2,2,2,2,2,2,2,2,2,2,2,2,2,2,2,2,2,2,2,2,2,2],[2,2,2,2,2,2,2,2,2,2,2,2,2,2,2,2,2,2,2,2,2,2,2,2,2,2,2,2,2,2,2,2,2,2,2,2,2,2,2,2,2,2,2,2,2,2,2,2,2,2],[2,2,2,2,2,2,2,2,2,2,2,2,2,2,2,2,2,2,2,2,2,2,2,2,2,2,2,2,2,2,2,2,2,2,2,2,2,2,2,2,2,2,2,2,2,2,2,2,2,2],[2,2,2,2,2,2,2,2,2,2,2,2,2,2,2,2,2,2,2,2,2,2,2,2,2,2,2,2,2,2,2,2,2,2,2,2,2,2,2,2,2,2,2,2,2,2,2,2,2,2],[2,2,2,2,2,2,2,2,2,2,2,2,2,2,2,2,2,2,2,2,2,2,2,2,2,2,2,2,2,2,2,2,2,2,2,2,2,2,2,2,2,2,2,2,2,2,2,2,2,2],[2,2,2,2,2,2,2,2,2,2,2,2,2,2,2,2,2,2,2,2,2,2,2,2,2,2,2,2,2,2,2,2,2,2,2,2,2,2,2,2,2,2,2,2,2,2,2,2,2,2],[2,2,2,2,2,2,2,2,2,2,2,2,2,2,2,2,2,2,2,2,2,2,2,2,2,2,2,2,2,2,2,2,2,2,2,2,2,2,2,2,2,2,2,2,2,2,2,2,2,2],[2,2,2,2,2,2,2,2,2,2,2,2,2,2,2,2,2,2,2,2,2,2,2,2,2,2,2,2,2,2,2,2,2,2,2,2,2,2,2,2,2,2,2,2,2,2,2,2,2,2],[2,2,2,2,2,2,2,2,2,2,2,2,2,2,2,2,2,2,2,2,2,2,2,2,2,2,2,2,2,2,2,2,2,2,2,2,2,2,2,2,2,2,2,2,2,2,2,2,2,2],[2,2,2,2,2,2,2,2,2,2,2,2,2,2,2,2,2,2,2,2,2,2,2,2,2,2,2,2,2,2,2,2,2,2,2,2,2,2,2,2,2,2,2,2,2,2,2,2,2,2],[2,2,2,2,2,2,2,2,2,2,2,2,2,2,2,2,2,2,2,2,2,2,2,2,2,2,2,2,2,2,2,2,2,2,2,9,0,0,0,0,10,2,2,2,2,2,2,2,2,2],[2,2,2,2,2,2,2,2,2,2,2,2,2,2,2,2,2,2,2,2,2,2,2,2,2,2,2,2,2,2,2,2,2,2,2,0,0,0,0,0,0,2,2,2,2,2,2,2,2,2],[2,2,2,2,2,2,2,9,0,0,0,0,0,0,0,0,0,0,0,0,0,0,0,0,0,0,0,0,0,0,0,0,0,0,0,0,0,0,0,0,0,0,0,0,10,2,2,2,2,2],[2,2,2,2,2,2,2,0,0,0,0,0,0,0,0,0,0,0,0,0,0,0,0,0,0,0,0,0,0,0,0,0,0,0,0,0,0,0,0,0,0,0,0,0,0,2,2,2,2,2],[2,2,2,2,2,2,2,0,0,0,0,0,0,0,0,0,0,0,0,0,0,0,0,0,0,0,0,0,0,0,0,0,0,0,0,0,0,0,0,0,0,0,0,0,0,2,2,2,2,2],[2,2,2,2,2,2,2,0,0,0,0,0,0,0,0,0,0,0,0,0,0,0,0,0,0,0,0,0,0,0,0,0,0,0,0,0,0,0,0,0,0,0,0,0,0,2,2,2,2,2],[2,2,2,2,2,2,2,0,0,0,0,0,0,0,0,0,0,0,0,0,0,0,0,0,0,0,0,0,0,0,0,0,0,0,0,0,0,0,0,0,0,0,0,0,0,2,2,2,2,2],[2,2,2,2,2,2,2,0,0,0,0,0,0,0,0,0,0,0,0,0,0,0,0,0,0,0,0,0,0,0,0,0,0,0,0,0,0,0,0,0,0,0,0,0,0,2,2,2,2,2],[2,2,2,2,2,2,2,0,0,0,0,0,0,0,0,0,0,0,0,0,0,0,0,0,0,0,0,0,0,0,0,0,0,0,0,0,0,0,0,0,0,0,0,0,0,2,2,2,2,2],[2,2,2,2,2,2,2,0,0,0,0,0,0,0,0,0,0,0,0,0,0,0,0,0,0,0,0,0,0,0,0,0,0,0,0,0,0,0,0,0,0,0,0,0,0,2,2,2,2,2],[2,2,2,2,2,2,2,0,0,0,0,0,0,0,0,0,0,0,0,0,0,0,0,0,0,0,0,0,0,0,0,0,0,0,0,0,0,0,0,0,0,0,0,0,0,2,2,2,2,2],[2,2,2,2,2,2,2,0,0,0,0,0,0,0,0,0,0,0,0,0,0,0,0,0,0,0,0,0,0,0,0,0,0,0,0,0,0,0,0,0,0,0,0,0,0,2,2,2,2,2],[2,2,2,2,2,2,2,0,0,0,0,0,0,0,0,0,0,0,0,0,0,0,0,0,0,0,0,0,0,0,0,0,0,0,0,0,0,0,0,0,0,0,0,0,0,2,2,2,2,2],[2,2,2,2,2,2,2,0,0,0,0,0,0,0,0,0,0,0,0,0,0,0,0,0,0,0,0,0,0,0,0,0,0,0,0,0,0,0,0,0,0,0,0,0,0,2,2,2,2,2],[2,2,2,2,2,2,2,0,0,0,0,0,0,0,0,0,0,0,0,0,0,0,0,0,0,0,0,0,0,0,0,0,0,0,0,0,0,0,0,0,0,0,0,0,0,2,2,2,2,2],[2,2,2,2,2,2,2,0,0,0,0,0,0,0,0,0,0,0,0,0,0,0,0,0,0,0,0,0,0,0,0,0,0,0,0,0,0,0,0,0,0,0,0,0,0,2,2,2,2,2],[2,2,2,2,2,2,2,0,0,0,0,0,0,0,0,0,0,0,0,0,0,0,0,0,0,0,0,0,0,0,0,0,0,0,0,0,0,0,0,0,0,0,0,0,0,2,2,2,2,2],[2,2,2,2,2,2,2,0,0,0,0,0,0,0,0,0,0,0,0,0,0,0,0,0,0,0,0,0,0,0,0,0,0,0,0,0,0,0,0,0,0,0,0,0,0,2,2,2,2,2],[2,2,2,2,2,2,2,0,0,0,0,0,0,0,0,0,0,0,0,0,0,0,0,0,0,0,0,0,0,0,0,0,0,0,0,0,0,0,0,0,0,0,0,0,0,2,2,2,2,2],[2,2,2,2,2,2,2,0,0,0,0,0,0,0,0,0,0,0,0,0,0,0,0,0,0,0,0,0,0,0,0,0,0,0,0,0,0,0,0,0,0,0,0,0,0,2,2,2,2,2],[2,2,2,2,2,2,2,0,0,0,0,0,0,0,0,0,0,0,0,0,0,0,0,0,0,0,0,0,0,0,0,0,0,0,0,0,0,0,0,0,0,0,0,0,0,2,2,2,2,2],[2,2,2,2,2,2,2,0,0,0,0,0,0,0,0,0,0,0,0,0,0,0,0,0,0,0,0,0,0,0,0,0,0,0,0,0,0,0,0,0,0,0,0,0,0,2,2,2,2,2],[2,2,2,2,2,2,2,0,0,0,0,0,0,0,0,0,0,0,0,0,0,0,0,0,0,0,0,0,0,0,0,0,0,0,0,0,0,0,0,0,0,0,0,0,0,2,2,2,2,2],[2,2,2,2,2,2,2,8,0,0,0,0,0,0,0,0,0,0,0,0,0,0,0,0,0,0,0,0,0,0,0,0,0,0,0,0,0,0,0,0,0,0,0,0,11,2,2,2,2,2],[2,2,2,2,2,2,2,2,2,2,2,2,2,2,2,2,2,2,2,2,8,0,0,0,0,0,0,0,0,11,2,2,2,2,2,2,2,2,2,2,2,2,2,2,2,2,2,2,2,2],[2,2,2,2,2,2,2,2,2,2,2,2,2,2,2,2,2,2,2,2,2,0,0,0,0,0,0,0,0,2,2,2,2,2,2,2,2,2,2,2,2,2,2,2,2,2,2,2,2,2],[2,2,2,2,2,2,2,2,2,2,2,2,2,2,2,2,2,2,2,2,2,0,0,0,0,0,0,0,0,2,2,2,2,2,2,2,2,2,2,2,2,2,2,2,2,2,2,2,2,2],[2,2,2,2,2,2,2,2,2,2,2,2,2,2,2,2,2,2,2,2,2,8,0,0,0,0,0,0,11,2,2,2,2,2,2,2,2,2,2,2,2,2,2,2,2,2,2,2,2,2],[2,2,2,2,2,2,2,2,2,2,2,2,2,2,2,2,2,2,2,2,2,2,2,2,2,2,2,2,2,2,2,2,2,2,2,2,2,2,2,2,2,2,2,2,2,2,2,2,2,2],[2,2,2,2,2,2,2,2,2,2,2,2,2,2,2,2,2,2,2,2,2,2,2,2,2,2,2,2,2,2,2,2,2,2,2,2,2,2,2,2,2,2,2,2,2,2,2,2,2,2],[2,2,2,2,2,2,2,2,2,2,2,2,2,2,2,2,2,2,2,2,2,2,2,2,2,2,2,2,2,2,2,2,2,2,2,2,2,2,2,2,2,2,2,2,2,2,2,2,2,2],[2,2,2,2,2,2,2,2,2,2,2,2,2,2,2,2,2,2,2,2,2,2,2,2,2,2,2,2,2,2,2,2,2,2,2,2,2,2,2,2,2,2,2,2,2,2,2,2,2,2],[2,2,2,2,2,2,2,2,2,2,2,2,2,2,2,2,2,2,2,2,2,2,2,2,2,2,2,2,2,2,2,2,2,2,2,2,2,2,2,2,2,2,2,2,2,2,2,2,2,2],[2,2,2,2,2,2,2,2,2,2,2,2,2,2,2,2,2,2,2,2,2,2,2,2,2,2,2,2,2,2,2,2,2,2,2,2,2,2,2,2,2,2,2,2,2,2,2,2,2,2],[2,2,2,2,2,2,2,2,2,2,2,2,2,2,2,2,2,2,2,2,2,2,2,2,2,2,2,2,2,2,2,2,2,2,2,2,2,2,2,2,2,2,2,2,2,2,2,2,2,2]]},{"id":9,"type":"HeightMap","name":"HeightMap","level":"postlight","width":50,"height":45,"visible":1,"tilesetName":"media\/map\/heightmap-tiles.png","repeat":false,"lighter":false,"distance":1,"yDistance":0,"tilesize":16,"moveSpeed":{"x":0,"y":0},"data":[[41,41,41,41,41,41,41,41,41,41,41,41,41,41,41,41,41,41,41,41,41,41,41,41,41,41,41,41,41,41,41,41,41,41,41,41,41,41,41,41,41,41,41,41,41,41,41,41,41,41],[41,41,41,41,41,41,41,41,41,41,41,41,41,41,41,41,41,41,41,41,41,41,41,41,41,41,41,41,41,41,41,41,41,41,41,41,41,41,41,41,41,41,41,41,41,41,41,41,41,41],[41,41,41,41,41,41,41,41,41,41,41,41,41,41,41,41,41,41,41,41,41,41,41,41,41,41,41,41,41,41,41,41,41,41,41,41,41,41,41,41,41,41,41,41,41,41,41,41,41,41],[41,41,41,41,41,41,41,41,41,41,41,41,41,41,41,41,41,41,41,41,41,41,41,41,41,41,41,41,41,41,41,41,41,41,41,41,41,41,41,41,41,41,41,41,41,41,41,41,41,41],[41,41,41,41,41,41,41,41,41,41,41,41,41,41,41,41,41,41,41,41,41,41,41,41,41,41,41,41,41,41,41,41,41,41,41,41,41,41,41,41,41,41,41,41,41,41,41,41,41,41],[41,41,41,41,41,41,41,41,41,41,41,41,41,41,41,41,41,41,41,41,41,41,41,41,41,41,41,41,41,41,41,41,41,41,41,41,41,41,41,41,41,41,41,41,41,41,41,41,41,41],[41,41,41,41,41,41,41,41,41,41,41,41,41,41,41,41,41,41,41,41,41,41,41,41,41,41,41,41,41,41,41,41,41,41,41,41,41,41,41,41,41,41,41,41,41,41,41,41,41,41],[41,41,41,41,41,41,41,41,41,41,41,41,41,41,41,41,41,41,41,41,41,41,41,41,41,41,41,41,41,41,41,41,41,41,41,41,41,41,41,41,41,41,41,41,41,41,41,41,41,41],[41,41,41,41,41,41,41,41,41,41,41,41,41,41,41,41,41,41,41,41,41,41,41,41,41,41,41,41,41,41,41,41,41,41,41,41,41,41,41,41,41,41,41,41,41,41,41,41,41,41],[41,41,41,41,41,41,41,41,41,41,41,41,41,41,41,41,41,41,41,41,41,41,41,41,41,41,41,41,41,41,41,41,41,41,41,41,41,41,41,41,41,41,41,41,41,41,41,41,41,41],[41,41,41,41,41,41,41,41,41,41,41,41,41,41,41,41,41,41,41,41,41,41,41,41,41,41,41,41,41,41,41,41,41,41,41,41,41,41,41,41,41,41,41,41,41,41,41,41,41,41],[41,41,41,41,41,41,41,41,41,41,41,41,41,41,41,41,41,41,41,41,41,41,41,41,41,41,41,41,41,41,41,41,41,41,41,41,41,41,41,41,41,41,41,41,41,41,41,41,41,41],[41,41,41,41,41,41,41,41,41,41,41,41,41,41,41,41,41,41,41,41,41,41,41,41,41,41,41,41,41,41,41,41,41,41,41,17,145,145,145,145,17,41,41,41,41,41,41,41,41,41],[41,41,41,41,41,41,41,41,41,41,41,41,41,41,41,41,41,41,41,41,41,41,41,41,41,41,41,41,41,41,41,41,41,41,42,17,145,145,145,145,17,42,41,42,41,41,41,41,41,41],[41,41,41,41,41,41,41,41,17,17,17,17,17,17,17,17,145,145,145,145,17,17,17,145,145,145,145,17,17,17,17,17,17,17,17,17,145,145,145,145,17,17,1,1,1,41,41,41,41,41],[41,41,41,41,41,41,41,17,17,17,17,17,17,17,17,17,145,145,145,145,17,17,145,145,145,145,145,145,17,17,17,17,17,17,17,17,145,145,145,145,17,17,1,1,1,41,41,41,41,41],[41,41,41,41,41,41,41,17,17,17,17,17,17,17,17,17,145,145,145,145,17,17,145,145,145,145,145,145,17,17,17,17,17,17,17,17,145,145,145,145,17,17,1,1,1,41,41,41,41,41],[41,41,41,41,41,41,41,17,17,17,17,17,17,17,17,17,145,145,145,145,17,17,17,145,145,145,145,17,17,17,17,17,17,17,17,17,17,145,145,17,17,17,1,1,1,41,41,41,41,41],[41,41,41,41,41,41,41,17,17,17,17,1,1,1,1,2,145,145,145,145,2,17,17,17,145,145,17,17,17,1,1,1,1,2,17,17,17,17,17,17,17,17,1,1,1,41,41,41,41,41],[41,41,41,41,41,41,41,17,17,17,17,1,1,1,1,1,145,145,145,145,1,1,17,17,17,17,17,17,1,1,1,1,1,2,17,17,17,17,17,17,17,17,1,1,1,41,41,41,41,41],[41,41,41,41,41,41,41,17,17,17,17,1,1,1,1,1,145,145,145,145,1,1,1,17,17,17,17,1,1,1,1,1,1,1,1,1,1,1,1,1,1,1,1,1,1,41,41,41,41,41],[41,41,41,41,41,41,41,17,17,17,17,1,1,1,1,1,145,145,145,145,2,1,2,17,17,17,17,1,1,1,1,1,1,1,1,1,1,1,1,1,1,1,1,1,1,41,41,41,41,41],[41,41,41,41,41,41,41,145,145,145,17,2,1,1,1,2,145,145,145,145,17,17,17,17,17,17,17,1,1,1,1,1,1,1,1,1,1,1,1,1,1,1,1,1,1,41,41,41,41,41],[41,41,41,41,41,41,41,145,145,145,145,145,145,145,145,145,145,145,145,145,145,17,17,17,17,17,17,17,17,17,17,17,17,17,17,17,17,17,17,17,17,17,1,1,1,41,41,41,41,41],[41,41,41,41,41,41,41,145,145,145,145,145,145,145,145,145,145,145,145,145,145,145,17,17,17,17,17,17,17,17,17,17,17,17,17,17,17,17,17,17,17,17,17,1,1,41,41,41,41,41],[41,41,41,41,41,41,41,145,145,145,145,145,145,145,145,145,145,145,145,145,145,145,17,17,17,17,17,17,17,17,17,17,17,17,17,17,17,17,17,17,17,17,17,1,1,41,41,41,41,41],[41,41,41,41,41,41,41,145,145,145,145,145,145,145,145,145,145,145,145,145,145,17,17,17,17,17,17,17,17,17,1,1,1,1,1,1,1,1,1,17,17,17,17,1,1,41,41,41,41,41],[41,41,41,41,41,41,41,145,145,145,17,2,1,1,1,1,1,1,1,2,17,17,17,17,17,17,17,17,17,17,1,1,1,1,1,1,1,1,1,17,17,17,17,1,1,41,41,41,41,41],[41,41,41,41,41,41,41,17,17,17,17,1,1,1,1,1,1,1,1,1,17,17,17,17,17,17,17,17,17,17,1,1,1,17,17,17,1,1,1,17,17,17,17,1,1,41,41,41,41,41],[41,41,41,41,41,41,41,17,17,17,17,1,1,1,1,1,1,1,1,1,17,17,17,17,17,17,17,17,17,17,1,1,1,17,17,17,1,1,1,17,17,17,17,1,1,41,41,41,41,41],[41,41,41,41,41,41,41,17,17,17,17,1,1,1,1,1,1,1,1,2,17,17,17,17,17,17,17,17,17,17,1,1,1,17,17,17,1,1,1,17,17,17,17,1,1,41,41,41,41,41],[41,41,41,41,41,41,41,17,17,17,17,17,17,17,17,17,17,17,17,17,17,17,17,17,17,17,17,17,17,17,1,1,1,1,1,1,1,1,1,17,17,17,17,1,1,41,41,41,41,41],[41,41,41,41,41,41,41,17,17,17,17,17,17,17,17,17,17,17,17,17,17,17,17,17,17,17,17,17,17,17,1,1,1,1,1,1,1,1,1,17,17,17,17,1,1,41,41,41,41,41],[41,41,41,41,41,41,41,17,17,17,17,17,17,17,17,17,17,17,17,17,17,17,17,17,17,17,17,17,17,17,17,17,17,17,17,17,17,17,17,17,17,17,17,1,1,41,41,41,41,41],[41,41,41,41,41,41,41,17,17,17,17,17,17,17,17,17,17,17,17,17,17,17,17,17,17,17,17,17,17,17,17,17,17,17,17,17,17,17,17,17,17,17,17,1,1,41,41,41,41,41],[41,41,41,41,41,41,41,17,17,17,17,17,17,17,17,17,17,17,17,17,17,17,17,17,145,145,17,17,17,17,17,17,17,17,17,17,17,17,17,17,17,17,17,1,1,41,41,41,41,41],[41,41,41,41,41,41,41,41,41,41,41,41,41,41,41,41,41,41,41,41,41,17,17,145,145,145,145,17,17,41,41,41,41,41,41,41,41,41,41,41,41,41,41,41,41,41,41,41,41,41],[41,41,41,41,41,41,41,41,41,41,41,41,41,41,41,41,41,41,41,41,41,17,17,145,145,145,145,17,17,41,41,41,41,41,41,41,41,41,41,41,41,41,41,41,41,41,41,41,41,41],[41,41,41,41,41,41,41,41,41,41,41,41,41,41,41,41,41,41,41,41,41,17,17,145,145,145,145,17,17,41,41,41,41,41,41,41,41,41,41,41,41,41,41,41,41,41,41,41,41,41],[41,41,41,41,41,41,41,41,41,41,41,41,41,41,41,41,41,41,41,41,41,17,17,145,145,145,145,17,17,41,41,41,41,41,41,41,41,41,41,41,41,41,41,41,41,41,41,41,41,41],[41,41,41,41,41,41,41,41,41,41,41,41,41,41,41,41,41,41,41,41,41,41,41,41,41,41,41,41,41,41,41,41,41,41,41,41,41,41,41,41,41,41,41,41,41,41,41,41,41,41],[41,41,41,41,41,41,41,41,41,41,41,41,41,41,41,41,41,41,41,41,41,41,41,41,41,41,41,41,41,41,41,41,41,41,41,41,41,41,41,41,41,41,41,41,41,41,41,41,41,41],[41,41,41,41,41,41,41,41,41,41,41,41,41,41,41,41,41,41,41,41,41,41,41,41,41,41,41,41,41,41,41,41,41,41,41,41,41,41,41,41,41,41,41,41,41,41,41,41,41,41],[41,41,41,41,41,41,41,41,41,41,41,41,41,41,41,41,41,41,41,41,41,41,41,41,41,41,41,41,41,41,41,41,41,41,41,41,41,41,41,41,41,41,41,41,41,41,41,41,41,41],[41,41,41,41,41,41,41,41,41,41,41,41,41,41,41,41,41,41,41,41,41,41,41,41,41,41,41,41,41,41,41,41,41,41,41,41,41,41,41,41,41,41,41,41,41,41,41,41,41,41]]},{"id":10,"type":"Light","name":"Light","level":"last","width":50,"height":45,"visible":1,"tilesetName":"media\/map\/lightmap-tiles.png","repeat":false,"lighter":false,"distance":1,"yDistance":0,"tilesize":16,"moveSpeed":{"x":0,"y":0},"data":[[0,0,0,0,0,0,0,0,0,0,0,0,0,0,0,0,0,0,0,0,0,0,0,0,0,0,0,0,0,0,0,0,0,0,0,0,0,0,0,0,0,0,0,0,0,0,0,0,0,0],[0,0,0,0,0,0,0,0,0,0,0,0,0,0,0,0,0,0,0,0,0,0,0,0,0,0,0,0,0,0,0,0,0,0,0,0,0,0,0,0,0,0,0,0,0,0,0,0,0,0],[0,0,0,0,0,0,0,0,0,0,0,0,0,0,0,0,0,0,0,0,0,0,0,0,0,0,0,0,0,0,0,0,0,0,0,0,0,0,0,0,0,0,0,0,0,0,0,0,0,0],[0,0,0,0,0,0,0,0,0,0,0,0,0,0,0,0,0,0,0,0,0,0,0,0,0,0,0,0,0,0,0,0,0,0,0,0,0,0,0,0,0,0,0,0,0,0,0,0,0,0],[0,0,0,0,0,0,0,0,0,0,0,0,0,0,0,0,0,0,0,0,0,0,0,0,0,0,0,0,0,0,0,0,0,0,0,0,0,0,0,0,0,0,0,0,0,0,0,0,0,0],[0,0,0,0,0,0,0,0,0,0,0,0,0,0,0,0,0,0,0,0,0,0,0,0,0,0,0,0,0,0,0,0,0,0,0,0,0,0,0,0,0,0,0,0,0,0,0,0,0,0],[0,0,0,0,0,0,0,0,0,0,0,0,0,0,0,0,0,0,0,0,0,0,0,0,0,0,0,0,0,0,0,0,0,0,0,0,0,0,0,0,0,0,0,0,0,0,0,0,0,0],[0,0,0,0,0,0,0,0,0,0,0,0,0,0,0,0,0,0,0,0,0,0,0,0,0,0,0,0,0,0,0,0,0,0,0,0,0,0,0,0,0,0,0,0,0,0,0,0,0,0],[0,0,0,0,0,0,0,0,0,0,0,0,0,0,0,0,0,0,0,0,0,0,0,0,0,0,0,0,0,0,0,0,0,0,0,0,0,0,0,0,0,0,0,0,0,0,0,0,0,0],[0,0,0,0,0,0,0,0,0,0,0,0,0,0,0,0,0,0,0,0,0,0,0,0,0,0,0,0,0,0,0,0,0,0,0,0,0,0,0,0,0,0,0,0,0,0,0,0,0,0],[0,0,0,0,0,0,0,0,0,0,0,0,0,0,0,0,0,0,0,0,0,0,0,0,0,0,0,0,0,0,0,0,0,0,0,0,0,0,0,0,0,0,0,0,0,0,0,0,0,0],[0,0,0,0,0,0,0,0,0,0,0,0,0,0,0,0,0,0,0,0,0,0,0,0,0,0,0,0,0,0,0,0,0,0,0,0,0,67,0,0,0,0,0,0,0,0,0,0,0,0],[0,0,0,0,0,0,0,0,0,0,0,0,0,0,0,0,0,0,0,0,0,0,0,0,0,0,0,0,0,0,0,0,0,0,0,0,0,0,0,0,0,0,0,0,0,0,0,0,0,0],[0,0,0,0,0,0,0,0,0,0,0,0,0,0,0,0,0,0,0,0,0,0,0,0,0,0,0,0,0,0,0,0,0,0,0,0,0,0,0,0,0,0,0,0,0,0,0,0,0,0],[0,0,0,0,0,0,0,0,0,0,0,0,0,0,0,0,0,0,0,0,0,0,0,0,0,0,0,0,0,0,0,0,0,0,0,0,0,0,0,0,0,0,0,0,0,0,0,0,0,0],[0,0,0,0,0,0,0,0,0,0,0,0,0,0,0,0,0,0,0,0,0,0,0,0,66,0,0,0,0,0,0,0,0,0,0,0,0,81,0,0,0,0,0,0,0,0,0,0,0,0],[0,0,0,0,0,0,0,0,0,0,0,0,0,0,0,0,0,0,0,0,0,0,0,0,0,0,0,0,0,0,0,0,0,0,0,0,0,0,0,0,0,0,0,0,0,0,0,0,0,0],[0,0,0,0,0,0,0,0,0,0,0,0,0,0,0,0,0,0,0,0,0,0,0,0,0,0,0,0,0,0,0,0,0,0,0,0,0,0,0,0,0,0,0,0,0,0,0,0,0,0],[0,0,0,0,0,0,0,0,0,0,0,0,20,0,19,0,0,0,0,0,0,0,0,0,0,0,0,0,0,0,19,0,19,0,0,0,0,0,0,0,0,0,0,0,0,0,0,0,0,0],[0,0,0,0,0,0,0,0,0,0,0,0,0,0,0,0,0,66,0,0,0,19,0,0,0,0,0,0,19,0,0,0,0,0,0,0,0,0,0,0,0,0,0,0,0,0,0,0,0,0],[0,0,0,0,0,0,0,0,0,0,0,0,0,0,0,0,0,0,0,0,0,0,0,0,0,0,0,0,0,0,0,0,0,0,0,0,19,0,0,19,0,0,0,0,0,0,0,0,0,0],[0,0,0,0,0,0,0,0,0,0,0,0,0,0,0,0,0,0,0,0,0,0,0,0,0,0,0,0,0,0,0,0,0,0,0,0,0,0,0,0,0,0,0,0,0,0,0,0,0,0],[0,0,0,0,0,0,0,0,0,0,0,0,0,0,0,0,0,0,0,0,0,0,0,0,0,0,0,0,0,0,0,0,0,0,0,0,0,0,0,0,0,0,0,0,0,0,0,0,0,0],[0,0,0,0,0,0,0,0,0,0,0,0,0,0,0,0,12,66,0,0,0,0,0,0,65,0,0,0,0,0,0,0,0,0,0,0,0,0,0,0,0,0,0,0,0,0,0,0,0,0],[0,0,0,0,0,0,0,0,0,0,0,0,2,0,0,0,0,0,0,0,0,0,0,0,0,0,0,0,0,0,0,0,0,0,0,2,0,0,0,0,0,0,0,0,0,0,0,0,0,0],[0,0,0,0,0,0,0,0,0,0,0,0,0,0,0,0,0,0,0,0,0,0,0,0,0,0,0,0,0,0,0,0,0,0,0,0,0,0,0,0,0,0,0,0,0,0,0,0,0,0],[0,0,0,0,0,0,0,0,0,0,0,0,0,0,0,0,0,0,0,0,0,0,0,0,0,0,0,0,0,0,0,0,19,0,19,0,19,0,0,0,0,0,0,0,0,0,0,0,0,0],[0,0,0,0,0,0,0,0,0,0,0,0,19,0,19,0,19,0,19,0,0,0,0,0,0,0,0,0,0,0,0,0,0,0,0,0,0,0,0,0,0,0,0,0,0,0,0,0,0,0],[0,0,0,0,0,0,0,0,0,0,0,0,0,0,0,0,0,0,0,0,0,0,0,0,0,0,0,0,0,0,0,0,0,0,12,0,0,0,0,0,0,0,0,0,0,0,0,0,0,0],[0,0,0,0,0,0,0,0,0,0,0,0,0,0,0,0,0,0,0,0,0,0,0,0,0,0,0,0,0,0,0,0,0,0,0,0,0,0,0,0,0,0,0,0,0,0,0,0,0,0],[0,0,0,0,0,0,0,0,0,0,0,0,0,0,0,0,0,0,0,0,0,0,0,0,0,0,0,0,0,0,0,0,0,2,0,0,0,0,0,0,0,0,0,0,0,0,0,0,0,0],[0,0,0,0,0,0,0,0,0,0,0,0,0,0,0,0,0,0,2,0,0,0,0,0,0,0,0,0,0,0,0,0,0,0,0,0,0,0,0,0,0,0,0,0,0,0,0,0,0,0],[0,0,0,0,0,0,0,0,0,0,0,0,0,0,0,0,0,0,0,0,0,0,0,0,0,0,0,0,0,0,0,0,0,0,0,0,0,0,0,0,0,0,0,0,0,0,0,0,0,0],[0,0,0,0,0,0,0,0,0,0,0,0,0,0,0,0,0,0,0,0,0,0,0,0,0,0,0,0,0,0,0,0,0,0,0,0,0,0,0,0,0,0,0,0,0,0,0,0,0,0],[0,0,0,0,0,0,0,0,0,0,0,0,0,0,0,0,0,0,0,0,0,0,0,0,0,0,0,0,0,0,0,0,0,0,0,0,0,0,0,0,0,0,0,0,0,0,0,0,0,0],[0,0,0,0,0,0,0,0,0,0,0,0,0,0,0,0,0,0,0,0,0,0,0,0,0,0,0,0,0,0,0,0,0,0,0,0,0,0,0,0,0,0,0,0,0,0,0,0,0,0],[0,0,0,0,0,0,0,0,0,0,0,0,0,0,0,0,0,0,0,0,0,0,0,0,2,0,0,0,0,0,0,0,0,0,0,0,0,0,0,0,0,0,0,0,0,0,0,0,0,0],[0,0,0,0,0,0,0,0,0,0,0,0,0,0,0,0,0,0,0,0,0,0,0,0,0,0,0,0,0,0,0,0,0,0,0,0,0,0,0,0,0,0,0,0,0,0,0,0,0,0],[0,0,0,0,0,0,0,0,0,0,0,0,0,0,0,0,0,0,0,0,0,0,0,0,0,0,0,0,0,0,0,0,0,0,0,0,0,0,0,0,0,0,0,0,0,0,0,0,0,0],[0,0,0,0,0,0,0,0,0,0,0,0,0,0,0,0,0,0,0,0,0,0,0,0,0,0,0,0,0,0,0,0,0,0,0,0,0,0,0,0,0,0,0,0,0,0,0,0,0,0],[0,0,0,0,0,0,0,0,0,0,0,0,0,0,0,0,0,0,0,0,0,0,0,0,0,0,0,0,0,0,0,0,0,0,0,0,0,0,0,0,0,0,0,0,0,0,0,0,0,0],[0,0,0,0,0,0,0,0,0,0,0,0,0,0,0,0,0,0,0,0,0,0,0,0,0,0,0,0,0,0,0,0,0,0,0,0,0,0,0,0,0,0,0,0,0,0,0,0,0,0],[0,0,0,0,0,0,0,0,0,0,0,0,0,0,0,0,0,0,0,0,0,0,0,0,0,0,0,0,0,0,0,0,0,0,0,0,0,0,0,0,0,0,0,0,0,0,0,0,0,0],[0,0,0,0,0,0,0,0,0,0,0,0,0,0,0,0,0,0,0,0,0,0,0,0,0,0,0,0,0,0,0,0,0,0,0,0,0,0,0,0,0,0,0,0,0,0,0,0,0,0],[0,0,0,0,0,0,0,0,0,0,0,0,0,0,0,0,0,0,0,0,0,0,0,0,0,0,0,0,0,0,0,0,0,0,0,0,0,0,0,0,0,0,0,0,0,0,0,0,0,0]]}],"attributes":{"saveMode":"","volume":1,"bgm":"silence","cameraInBounds":true,"map-sounds":"FINAL_DUNGEON_INSIDE","mapStyle":"final-dng-inner","weather":"FINAL_DNG_INNER","npcRunners":"","area":"final-dng","oobSound":"HOLE"},"screen":{"x":-266,"y":141}}